{
  "VoicePacks": [
    {
      "Format": "1.0.0",
      "VoicePackId": "Dictionary.Lewis.tr-TR",
      "VoicePackName": "Dictionary (Lewis - tr-TR)",
      "Character": "Lewis",
      "Language": "tr-TR",
      "Entries": [
        {
          "DialogueFrom": "AcceptBirthdayGift_Negative",
          "DialogueText": "Aman, yaşlı Başkan'ın doğum gününü hatırlamışsın... Bu da ne?",
          "AudioPath": "assets/tr-TR/Lewis/1.ogg"
        },
        {
          "DialogueFrom": "AcceptBirthdayGift_Negative_1",
          "DialogueText": "Şey... Ne derler bilirsin, 'Düşünmen yeter.'",
          "AudioPath": "assets/tr-TR/Lewis/2.ogg"
        },
        {
          "DialogueFrom": "AcceptBirthdayGift_Positive",
          "DialogueText": "Aa. Çok düşüncelisin. Bu güzel bir hediye!",
          "AudioPath": "assets/tr-TR/Lewis/3.ogg"
        },
        {
          "DialogueFrom": "AcceptGift_(O)StardropTea",
          "DialogueText": "Hayatım boyunca birçok çay denedim ama hiçbiri bu kadar nadir ve özel değildi. Teşekkürler!",
          "AudioPath": "assets/tr-TR/Lewis/4.ogg"
        },
        {
          "DialogueFrom": "cc_Begin",
          "DialogueText": "*koklar*... *koklar*... Ah, Halkevi'nde zaman geçirdiğini görüyorum. Birisinin orayla ilgilendiğini bilmek güzel.",
          "AudioPath": "assets/tr-TR/Lewis/5.ogg"
        },
        {
          "DialogueFrom": "cc_Bridge",
          "DialogueText": "Nasıl olduysa taş ocağına giden köprü tamir edilmiş.",
          "AudioPath": "assets/tr-TR/Lewis/6.ogg"
        },
        {
          "DialogueFrom": "cc_Bridge_1",
          "DialogueText": "Şaşkınım... Tamir etmek için koca bir ekip gerekmiş olmalı!",
          "AudioPath": "assets/tr-TR/Lewis/7.ogg"
        },
        {
          "DialogueFrom": "cc_Bridge_2",
          "DialogueText": "Bunu kim yapmış olabilir?",
          "AudioPath": "assets/tr-TR/Lewis/8.ogg"
        },
        {
          "DialogueFrom": "cc_Bus",
          "DialogueText": ", duydun mu? Bir gece ansızın eski otobüs çalışmaya başladı!",
          "AudioPath": "assets/tr-TR/Lewis/9.ogg"
        },
        {
          "DialogueFrom": "cc_Bus_1",
          "DialogueText": "O eski şey 10 yıldan fazla zamandır yatıyordu öyle... Bu gerçekten hayret verici bir gizem.",
          "AudioPath": "assets/tr-TR/Lewis/10.ogg"
        },
        {
          "DialogueFrom": "cc_Complete",
          "DialogueText": "Topluluğumuzla hiç bu kadar gurur duymamıştım. Pelikan Kasabası'na çok hizmet ettin, .",
          "AudioPath": "assets/tr-TR/Lewis/11.ogg"
        },
        {
          "DialogueFrom": "cropMatured_24",
          "DialogueText": "Selam, dün gece gönderi kutuna uğradım ve ilk yaban havuçlarının hazır olduğunu gördüm. Tebrikler!",
          "AudioPath": "assets/tr-TR/Lewis/12.ogg"
        },
        {
          "DialogueFrom": "cropMatured_254",
          "DialogueText": "çiftliğinin kavunları şahane gözüküyor!",
          "AudioPath": "assets/tr-TR/Lewis/13.ogg"
        },
        {
          "DialogueFrom": "cropMatured_254_1",
          "DialogueText": "Büyükbabanın en sevdiği ekin de buydu, biliyor muydun?",
          "AudioPath": "assets/tr-TR/Lewis/14.ogg"
        },
        {
          "DialogueFrom": "cropMatured_276",
          "DialogueText": "'Güzü' bir bal kabağı kadar iyi gösteren bir şey yok, sence de öyle değil mi?",
          "AudioPath": "assets/tr-TR/Lewis/15.ogg"
        },
        {
          "DialogueFrom": "divorced_once",
          "DialogueText": "Boşanma işlemleri tamamlandı. İşlerin yolunda gitmemesine üzüldüm...",
          "AudioPath": "assets/tr-TR/Lewis/16.ogg"
        },
        {
          "DialogueFrom": "divorced_twice",
          "DialogueText": "Yine mi boşanıyorsun? Hadi ama ... Kiminle evleneceğine biraz daha dikkat etmelisin...",
          "AudioPath": "assets/tr-TR/Lewis/17.ogg"
        },
        {
          "DialogueFrom": "event_secret1",
          "DialogueText": "Teşekkürler, . Bunu unutmayacağım.",
          "AudioPath": "assets/tr-TR/Lewis/18.ogg"
        },
        {
          "DialogueFrom": "event_secret2",
          "DialogueText": "*ağlar* Bunu yaptığına inanamıyorum...",
          "AudioPath": "assets/tr-TR/Lewis/19.ogg"
        },
        {
          "DialogueFrom": "event_secret2_1",
          "DialogueText": "Çok kötüsün.",
          "AudioPath": "assets/tr-TR/Lewis/20.ogg"
        },
        {
          "DialogueFrom": "fall_12",
          "DialogueText": "Çiftliğinde arı kovanı var mı?",
          "AudioPath": "assets/tr-TR/Lewis/21.ogg"
        },
        {
          "DialogueFrom": "fall_12_1",
          "DialogueText": "Eğer kovanı çiçeklerin yanına koyarsan farklı türlerde bal edinebilirsin.",
          "AudioPath": "assets/tr-TR/Lewis/22.ogg"
        },
        {
          "DialogueFrom": "fall_19",
          "DialogueText": "Bazen yerde bir şey mi gömülü bilemiyorsun. Gözün açık olsun.",
          "AudioPath": "assets/tr-TR/Lewis/23.ogg"
        },
        {
          "DialogueFrom": "fall_Fri",
          "DialogueText": "Umarım çitflikte işler yolundadır.",
          "AudioPath": "assets/tr-TR/Lewis/24.ogg"
        },
        {
          "DialogueFrom": "fall_Fri4",
          "DialogueText": "Gus'ın 'gizli' makarna sosunu denedin mi?",
          "AudioPath": "assets/tr-TR/Lewis/25.ogg"
        },
        {
          "DialogueFrom": "fall_Fri4_1",
          "DialogueText": "...İçindekiler gizli olabilir ama kokusu gizli değil.",
          "AudioPath": "assets/tr-TR/Lewis/26.ogg"
        },
        {
          "DialogueFrom": "fall_Fri4_2",
          "DialogueText": "Sonra görüşürüz.",
          "AudioPath": "assets/tr-TR/Lewis/27.ogg"
        },
        {
          "DialogueFrom": "fall_Mon",
          "DialogueText": "Bazı kasaba sakinleri yabancılara karşı tedbirli davranırlar. Sana açılmadan önce güvenlerini kazanman gerekiyor.",
          "AudioPath": "assets/tr-TR/Lewis/28.ogg"
        },
        {
          "DialogueFrom": "fall_Mon_1",
          "DialogueText": "Israrlı ol, güvenlerini kazanacağına eminim.",
          "AudioPath": "assets/tr-TR/Lewis/29.ogg"
        },
        {
          "DialogueFrom": "fall_Sun",
          "DialogueText": "Çitflikte konusunda elinden geleni yapıyor musun, ? Eğer iyi bir yurttaş olmak istiyorsan farklı alanlarda başarı elde etmen gerekiyor.",
          "AudioPath": "assets/tr-TR/Lewis/30.ogg"
        },
        {
          "DialogueFrom": "fall_Thu",
          "DialogueText": "Salon akşamları çok canlı oluyor.",
          "AudioPath": "assets/tr-TR/Lewis/31.ogg"
        },
        {
          "DialogueFrom": "fall_Thu_1",
          "DialogueText": "Ara sıra uğramak ve son gelişmeleri öğrenmek iyi oluyor.",
          "AudioPath": "assets/tr-TR/Lewis/32.ogg"
        },
        {
          "DialogueFrom": "fall_Town_57_40",
          "DialogueText": "Hım... Odun yongamda küçük, tuhaf mantarlar çıkmaya başladı. Acaba hangi cins bunlar?Günaydın! Yavaş yavaş soğuk gelmeye başladı, bu yüzden bahçeme tatlı tatlı veda ediyorum.",
          "AudioPath": "assets/tr-TR/Lewis/33.ogg"
        },
        {
          "DialogueFrom": "fall_Town_57_40_1",
          "DialogueText": "Ah, kasabaya erken gelmişsin! Çiftlikte işler bitti mi?",
          "AudioPath": "assets/tr-TR/Lewis/34.ogg"
        },
        {
          "DialogueFrom": "fall_Tue",
          "DialogueText": "20 yıl önce yılın bu zamanı ilk kez Başkan olmuştum.",
          "AudioPath": "assets/tr-TR/Lewis/35.ogg"
        },
        {
          "DialogueFrom": "fall_Tue_1",
          "DialogueText": "Yaşlandığımı hissediyorum.",
          "AudioPath": "assets/tr-TR/Lewis/36.ogg"
        },
        {
          "DialogueFrom": "fall_Wed",
          "DialogueText": "Kasaba için önerin varsa, benim dilek kutuma bırak.",
          "AudioPath": "assets/tr-TR/Lewis/37.ogg"
        },
        {
          "DialogueFrom": "fall_Wed_1",
          "DialogueText": "Ah, doğru... benim dilek kutum yoktu.",
          "AudioPath": "assets/tr-TR/Lewis/38.ogg"
        },
        {
          "DialogueFrom": "fall_Wed2",
          "DialogueText": "Her çarşamba, kahvaltıda karabuğday gözlemesi ve kahve gömerim. Şu bekâr hayatımı ilginçleştirmek için bu geleneği sürdürüyorum.",
          "AudioPath": "assets/tr-TR/Lewis/39.ogg"
        },
        {
          "DialogueFrom": "Fri",
          "DialogueText": "Umarım çiftliğinde işler yolunda gidiyordur. Kuruduğunu görmek istemezdim.",
          "AudioPath": "assets/tr-TR/Lewis/40.ogg"
        },
        {
          "DialogueFrom": "GreenRain",
          "DialogueText": "Az önce Vali Bey ile telefonda konuştum... Görünüşe göre bu yağmur tamamen zararsızmış. Sadece doğanın alışılmadık bir olayıymış.",
          "AudioPath": "assets/tr-TR/Lewis/41.ogg"
        },
        {
          "DialogueFrom": "GreenRain_1",
          "DialogueText": "Yine de kasaba halkı panik yapıyor. Bu hiç iyi değil...",
          "AudioPath": "assets/tr-TR/Lewis/42.ogg"
        },
        {
          "DialogueFrom": "GreenRain_2",
          "DialogueText": "Sanırım bu alışılmadık yağmurları her yıl bekleyebiliriz. Bunun sadece doğanın bir parçası olduğunu bilince herkesin daha sakin olduğunu düşünüyorum.",
          "AudioPath": "assets/tr-TR/Lewis/43.ogg"
        },
        {
          "DialogueFrom": "GreenRainFinished",
          "DialogueText": "Bu, küçük kasabamız için oldukça heyecan vericiydi! Herkesin iyi olmasına gerçekten sevindim.",
          "AudioPath": "assets/tr-TR/Lewis/44.ogg"
        },
        {
          "DialogueFrom": "GreenRainFinished_1",
          "DialogueText": "Bir daha yağarsa bu kadar paniklemeyiz. Dünyanın sonu gelmedi ya!",
          "AudioPath": "assets/tr-TR/Lewis/45.ogg"
        },
        {
          "DialogueFrom": "Introduction",
          "DialogueText": "Büyükbabanın barakasında ilk gecen nasıldı?",
          "AudioPath": "assets/tr-TR/Lewis/46.ogg"
        },
        {
          "DialogueFrom": "Introduction_1",
          "DialogueText": "Büyükbaban o eski yataktan şikayet ederdi hep. Ama bence içten içe evi seviyordu.",
          "AudioPath": "assets/tr-TR/Lewis/47.ogg"
        },
        {
          "DialogueFrom": "joja_Begin",
          "DialogueText": "Eh, eski Halkevi artık yok... Devir değişiyor. Her iyi şeyin bir sonu var... Yine de bir kaybetmişlik hissediyorum.",
          "AudioPath": "assets/tr-TR/Lewis/48.ogg"
        },
        {
          "DialogueFrom": "joja_Begin_1",
          "DialogueText": "Umarım bu olay Başkan olarak beni etkilemez.",
          "AudioPath": "assets/tr-TR/Lewis/49.ogg"
        },
        {
          "DialogueFrom": "married",
          "DialogueText": "Tebrik ederim . Sen ve için büyük bir adım. Kasabamıza kök salmış oldun!",
          "AudioPath": "assets/tr-TR/Lewis/50.ogg"
        },
        {
          "DialogueFrom": "married_twice",
          "DialogueText": "Tekrardan tebrikler .",
          "AudioPath": "assets/tr-TR/Lewis/51.ogg"
        },
        {
          "DialogueFrom": "Mon",
          "DialogueText": "Bizim gibi çiftçi olmayanlar için bile tam bahçeyle uğraşma mevsimi.",
          "AudioPath": "assets/tr-TR/Lewis/52.ogg"
        },
        {
          "DialogueFrom": "Mon_1",
          "DialogueText": "Vadi, en çok yetişen bahar çiçekleri ile ünlüdür!",
          "AudioPath": "assets/tr-TR/Lewis/53.ogg"
        },
        {
          "DialogueFrom": "movieTheater",
          "DialogueText": "Sinema salonu, gençlerin yüzünü gülümsetiyor.",
          "AudioPath": "assets/tr-TR/Lewis/54.ogg"
        },
        {
          "DialogueFrom": "movieTheater_1",
          "DialogueText": "Başarılı bir sinema salonunun, bölge ekonomisine büyük faydası olur. Umarım şu modern filmlerde sakıncalı şeyler yoktur.",
          "AudioPath": "assets/tr-TR/Lewis/55.ogg"
        },
        {
          "DialogueFrom": "pamHouseUpgrade",
          "DialogueText": ", Pam ve Penny için ne yaptığını duydum... İşte *bu* Pelikan Kasabası'nda görmeyi sevdiğim toplum dayanışması!",
          "AudioPath": "assets/tr-TR/Lewis/56.ogg"
        },
        {
          "DialogueFrom": "pamHouseUpgradeAnonymous",
          "DialogueText": ", duydun mu? Birisi Pam ve Penny'e ev yapması için Robin'e para ödemiş. Gerçi Robin bana kim olduğunu söylemiyor.",
          "AudioPath": "assets/tr-TR/Lewis/57.ogg"
        },
        {
          "DialogueFrom": "pamHouseUpgradeAnonymous_1",
          "DialogueText": "Kim öderse ödesin, Pelikan Kasabası'nda böyle toplum dayanışması görmeyi seviyorum!",
          "AudioPath": "assets/tr-TR/Lewis/58.ogg"
        },
        {
          "DialogueFrom": "Resort",
          "DialogueText": ", beni etkiledin. Burayı gerçekten adam etmişsin!",
          "AudioPath": "assets/tr-TR/Lewis/59.ogg"
        },
        {
          "DialogueFrom": "Resort_Bar",
          "DialogueText": "Hehe... Gus yine havaya girmiş.",
          "AudioPath": "assets/tr-TR/Lewis/60.ogg"
        },
        {
          "DialogueFrom": "Resort_Chair",
          "DialogueText": "Hehe... buraya bakar mısın? Nasıl yaptın bilmiyorum ama bu küçük tatil yeri tüm kasabanın dilinde.",
          "AudioPath": "assets/tr-TR/Lewis/61.ogg"
        },
        {
          "DialogueFrom": "Resort_Leaving",
          "DialogueText": "Herkes binsin! Vadiye geri dönüyoruz!",
          "AudioPath": "assets/tr-TR/Lewis/62.ogg"
        },
        {
          "DialogueFrom": "Resort_Shore",
          "DialogueText": "Bunun gibi tatil fırsatları bölge ekonomisine büyük katkılarda bulunabilir!",
          "AudioPath": "assets/tr-TR/Lewis/63.ogg"
        },
        {
          "DialogueFrom": "Resort_Shore_1",
          "DialogueText": "Uzun süre güneş altında kalmasam iyi olur, yoksa burnum kuruyabilir.",
          "AudioPath": "assets/tr-TR/Lewis/64.ogg"
        },
        {
          "DialogueFrom": "Saloon",
          "DialogueText": "İyi akşamlar! Kasaba halkı ile sosyalleşmen çok güzel.",
          "AudioPath": "assets/tr-TR/Lewis/65.ogg"
        },
        {
          "DialogueFrom": "Saloon_1",
          "DialogueText": "Ara sıra uğramak ve haberleri öğrenmek iyi oluyor.",
          "AudioPath": "assets/tr-TR/Lewis/66.ogg"
        },
        {
          "DialogueFrom": "Saloon_Entry",
          "DialogueText": "Merhaba, Gus!",
          "AudioPath": "assets/tr-TR/Lewis/67.ogg"
        },
        {
          "DialogueFrom": "Saloon4",
          "DialogueText": "İyi akşamlar, ! Seni salonda takılırken görmek ne güzel, ara sıra mola vermek lazım.",
          "AudioPath": "assets/tr-TR/Lewis/68.ogg"
        },
        {
          "DialogueFrom": "Saloon4_1",
          "DialogueText": "Büyükbaban çok sıkı çalışırdı... Onun şerefine bu akşam bir bira daha içeceğim.",
          "AudioPath": "assets/tr-TR/Lewis/69.ogg"
        },
        {
          "DialogueFrom": "Sat",
          "DialogueText": "Sence de herkes hafta sonu biraz daha mutlu görünmüyor mu?",
          "AudioPath": "assets/tr-TR/Lewis/70.ogg"
        },
        {
          "DialogueFrom": "Sat_1",
          "DialogueText": "Gerçi ben haftanın yedi gün iş başındayım.",
          "AudioPath": "assets/tr-TR/Lewis/71.ogg"
        },
        {
          "DialogueFrom": "spring_10",
          "DialogueText": "Ah... Sabahları bir bardak demli çay gibisi yok.",
          "AudioPath": "assets/tr-TR/Lewis/72.ogg"
        },
        {
          "DialogueFrom": "spring_3",
          "DialogueText": "Bahar ekini ekmedin mi henüz? Mevsim sonsuza kadar sürmeyecek, bunu biliyorsun değil mi?.",
          "AudioPath": "assets/tr-TR/Lewis/73.ogg"
        },
        {
          "DialogueFrom": "summer_Fri",
          "DialogueText": "Hım... Acaba bugün birinin doğum günü olabilir mi? Pierre'in dükkanındaki takvime göz atsam iyi olur.",
          "AudioPath": "assets/tr-TR/Lewis/74.ogg"
        },
        {
          "DialogueFrom": "summer_Mon",
          "DialogueText": "Bahçıvanlık benim hobim. Bu yüzden sıcak havayı iple çekiyorum.",
          "AudioPath": "assets/tr-TR/Lewis/75.ogg"
        },
        {
          "DialogueFrom": "summer_Sun",
          "DialogueText": "Çiftliğinde yaban mersini yetiştiriyor musun?",
          "AudioPath": "assets/tr-TR/Lewis/76.ogg"
        },
        {
          "DialogueFrom": "summer_Sun_1",
          "DialogueText": "Taze yaban mersinine bayılıyorum.:Lewis:258",
          "AudioPath": "assets/tr-TR/Lewis/77.ogg"
        },
        {
          "DialogueFrom": "summer_Thu",
          "DialogueText": "Haftada bir kere de olsa uğrayıp takılıyorum ve Gus'ın otantik çubuk makarnasını yiyorum.",
          "AudioPath": "assets/tr-TR/Lewis/78.ogg"
        },
        {
          "DialogueFrom": "summer_Town_57_40",
          "DialogueText": "Ah, çiçeklerim güzelcene büyüyor!Günaydın! Çiy düşen zambakların güzel kokusunu alıyor musun?",
          "AudioPath": "assets/tr-TR/Lewis/79.ogg"
        },
        {
          "DialogueFrom": "summer_Town_57_40_1",
          "DialogueText": "Saat erken ama hava sıcak. Benim gibi bir ihtiyara da sıcak hava iyi geliyor, hehe!",
          "AudioPath": "assets/tr-TR/Lewis/80.ogg"
        },
        {
          "DialogueFrom": "summer_Tue",
          "DialogueText": "Nasıl mı Başkan oldum? Uzun hikaye.",
          "AudioPath": "assets/tr-TR/Lewis/81.ogg"
        },
        {
          "DialogueFrom": "summer_Tue_1",
          "DialogueText": "İkimiz de hikaye anlatmak için çok meşgulüz.",
          "AudioPath": "assets/tr-TR/Lewis/82.ogg"
        },
        {
          "DialogueFrom": "summer_Wed",
          "DialogueText": "Ayışığı denizanaları yakında burada olur. Vadideki en sevdiğim olaylardan biri de onların gelişi.",
          "AudioPath": "assets/tr-TR/Lewis/83.ogg"
        },
        {
          "DialogueFrom": "Sun",
          "DialogueText": "20 yılı aşkın süredir Pelikan Kasabası'nın Başkanıyım!",
          "AudioPath": "assets/tr-TR/Lewis/84.ogg"
        },
        {
          "DialogueFrom": "Sun_1",
          "DialogueText": "Seçim zamanı kimse bana karşı aday olmuyor bile. Bunun işimi iyi yaptığım anlamına geldiğini düşünmeyi seviyorum.",
          "AudioPath": "assets/tr-TR/Lewis/85.ogg"
        },
        {
          "DialogueFrom": "Sun_2",
          "DialogueText": "Başkan olmak acayip bir şey.",
          "AudioPath": "assets/tr-TR/Lewis/86.ogg"
        },
        {
          "DialogueFrom": "Thu",
          "DialogueText": "Salon akşamları çok canlı oluyor. Bazen müzik kutusuna bozukluk bile atıyoruz. *güler*",
          "AudioPath": "assets/tr-TR/Lewis/87.ogg"
        },
        {
          "DialogueFrom": "Thu_1",
          "DialogueText": "Haftada bir kere de olsa oraya gidiyorum.",
          "AudioPath": "assets/tr-TR/Lewis/88.ogg"
        },
        {
          "DialogueFrom": "Town_57_40",
          "DialogueText": "Erkenden kasabaya uğruyorsun demek. Çiftlik işleri bitti mi?",
          "AudioPath": "assets/tr-TR/Lewis/89.ogg"
        },
        {
          "DialogueFrom": "Town_57_40_1",
          "DialogueText": "Günaydınlar, her zamanki gibi bahçeyi kontrol ediyorum.Hım... bunlar yaprak biti mi?",
          "AudioPath": "assets/tr-TR/Lewis/90.ogg"
        },
        {
          "DialogueFrom": "Town_57_40_2",
          "DialogueText": "Hım... Umarım bunlar yaprak böcekleri değildir...",
          "AudioPath": "assets/tr-TR/Lewis/91.ogg"
        },
        {
          "DialogueFrom": "Tue",
          "DialogueText": "Satmak istediğin şeyleri evinin yanındaki kutuya koy.",
          "AudioPath": "assets/tr-TR/Lewis/92.ogg"
        },
        {
          "DialogueFrom": "Tue_1",
          "DialogueText": "Oraya neler koyacağını merak ediyorum.",
          "AudioPath": "assets/tr-TR/Lewis/93.ogg"
        },
        {
          "DialogueFrom": "Tue2",
          "DialogueText": "Her mevsimin başında, önceki mevsimden kalan ölü ekinleri biçmen gerekir. En kolay tırpanla biçersin.",
          "AudioPath": "assets/tr-TR/Lewis/94.ogg"
        },
        {
          "DialogueFrom": "Wed",
          "DialogueText": "Hım... vergiler... *mırıldanır* ...bahar şölen harcamaları... *mırıldanır*...",
          "AudioPath": "assets/tr-TR/Lewis/95.ogg"
        },
        {
          "DialogueFrom": "Wed_1",
          "DialogueText": "Efendim?",
          "AudioPath": "assets/tr-TR/Lewis/96.ogg"
        },
        {
          "DialogueFrom": "willyCrabs",
          "DialogueText": "*koklar*... *koklar*... Kokuyu alıyor musun? Sabahtan beri burnuma taze pişmiş yengeç kokusu gelip duruyor...",
          "AudioPath": "assets/tr-TR/Lewis/97.ogg"
        },
        {
          "DialogueFrom": "winter_1",
          "DialogueText": "Kış geldi. Bu, kasaba sakinlerinin zamanınlarının çoğunu evlerinde geçireceği anlamına geliyor.",
          "AudioPath": "assets/tr-TR/Lewis/98.ogg"
        },
        {
          "DialogueFrom": "winter_1_1",
          "DialogueText": "En azından onları nerede bulacağımı biliyorum!",
          "AudioPath": "assets/tr-TR/Lewis/99.ogg"
        },
        {
          "DialogueFrom": "winter_Fri6",
          "DialogueText": "Hiç evlenmedim. Bir ailem yok. Başkan olmak için yaşıyorum.",
          "AudioPath": "assets/tr-TR/Lewis/100.ogg"
        },
        {
          "DialogueFrom": "winter_Fri6_1",
          "DialogueText": "Değer mi?",
          "AudioPath": "assets/tr-TR/Lewis/101.ogg"
        },
        {
          "DialogueFrom": "winter_Fri6_2",
          "DialogueText": "...*iç çeker*...",
          "AudioPath": "assets/tr-TR/Lewis/102.ogg"
        },
        {
          "DialogueFrom": "winter_Mon",
          "DialogueText": "Bir yıl daha bitmek üzere!",
          "AudioPath": "assets/tr-TR/Lewis/103.ogg"
        },
        {
          "DialogueFrom": "winter_Mon_1",
          "DialogueText": "Umarım üretken bir yıl geçirmişsindir!",
          "AudioPath": "assets/tr-TR/Lewis/104.ogg"
        },
        {
          "DialogueFrom": "winter_Sun",
          "DialogueText": "Selam, ! Bugün nasılsın?",
          "AudioPath": "assets/tr-TR/Lewis/105.ogg"
        },
        {
          "DialogueFrom": "winter_Sun_1",
          "DialogueText": "Marnie'yi görürsen selam söylediğimi ilet.",
          "AudioPath": "assets/tr-TR/Lewis/106.ogg"
        },
        {
          "DialogueFrom": "winter_Tue",
          "DialogueText": "Önümüzdeki yıl için kasabayı geliştirecek bir plan hazırlamam gerekiyor!",
          "AudioPath": "assets/tr-TR/Lewis/107.ogg"
        },
        {
          "DialogueFrom": "winter_Wed",
          "DialogueText": "Kar bile olsa her gece gelip ürünlerini alacağım.",
          "AudioPath": "assets/tr-TR/Lewis/108.ogg"
        },
        {
          "DialogueFrom": "winter_Wed_1",
          "DialogueText": "Kış mevsiminde bile para kazanman gerekiyor!",
          "AudioPath": "assets/tr-TR/Lewis/109.ogg"
        },
        {
          "DialogueFrom": "wonGrange",
          "DialogueText": "Çiftlik Sergisini kazandığın için tebrikler.",
          "AudioPath": "assets/tr-TR/Lewis/110.ogg"
        },
        {
          "DialogueFrom": "wonGrange_1",
          "DialogueText": "Hehe... Aramızda kalsın ama bence Pierre'in biraz daha ayaklarını yere basması gerek!",
          "AudioPath": "assets/tr-TR/Lewis/111.ogg"
        },
        {
          "DialogueFrom": "Event:BusStop/60367/u 0",
          "DialogueText": "Ah, yeni çiftçimiz gelmiş!",
          "AudioPath": "assets/tr-TR/Lewis/112.ogg"
        },
        {
          "DialogueFrom": "Event:BusStop/60367/u 0_1",
          "DialogueText": "Hoş geldin! Ben Lewis, Pelikan Kasabası'nın Başkanıyım.",
          "AudioPath": "assets/tr-TR/Lewis/113.ogg"
        },
        {
          "DialogueFrom": "Event:BusStop/60367/u 0_1_1",
          "DialogueText": "Biliyor musun, herkes seni sorup duruyordu.",
          "AudioPath": "assets/tr-TR/Lewis/114.ogg"
        },
        {
          "DialogueFrom": "Event:BusStop/60367/u 0_1_2",
          "DialogueText": "Sonuçta buraya her gün biri taşınmıyor. Bu bizim için oldukça büyük bir olay!",
          "AudioPath": "assets/tr-TR/Lewis/115.ogg"
        },
        {
          "DialogueFrom": "Event:BusStop/60367/u 0_2",
          "DialogueText": "Demek büyükbabanın eski barakasına taşınıyorsun.",
          "AudioPath": "assets/tr-TR/Lewis/116.ogg"
        },
        {
          "DialogueFrom": "Event:BusStop/60367/u 0_2_1",
          "DialogueText": "Güzel bir ev... fazlasıyla 'hoyrat'.",
          "AudioPath": "assets/tr-TR/Lewis/117.ogg"
        },
        {
          "DialogueFrom": "Event:BusStop/60367/u 0_3",
          "DialogueText": "Onu dinleme, . Sana ev geliştirmelerinden satmak istediği için moralini bozmaya çalışıyor.",
          "AudioPath": "assets/tr-TR/Lewis/118.ogg"
        },
        {
          "DialogueFrom": "Event:BusStop/60367/u 0_4",
          "DialogueText": "Her neyse... Uzun yolculuğun ardından yorulmuş olmalısın. Biraz dinlenmelisin.",
          "AudioPath": "assets/tr-TR/Lewis/119.ogg"
        },
        {
          "DialogueFrom": "Event:BusStop/60367/u 0_4_1",
          "DialogueText": "Yarın kasabaya inip kendini tanıtırsın.",
          "AudioPath": "assets/tr-TR/Lewis/120.ogg"
        },
        {
          "DialogueFrom": "Event:BusStop/60367/u 0_4_2",
          "DialogueText": "Kasaba halkı bunu takdir edecektir.",
          "AudioPath": "assets/tr-TR/Lewis/121.ogg"
        },
        {
          "DialogueFrom": "Event:BusStop/60367/u 0_5",
          "DialogueText": "Ah, az kalsın unutuyordum. Satılacak bir şeyin olursa bu kutuya koyman yeterli. Geceleri almaya gelirim.",
          "AudioPath": "assets/tr-TR/Lewis/122.ogg"
        },
        {
          "DialogueFrom": "Event:BusStop/60367/u 0_5_1",
          "DialogueText": "İyi şanslar!",
          "AudioPath": "assets/tr-TR/Lewis/123.ogg"
        },
        {
          "DialogueFrom": "Event:BusStop/60367/u 0_alt",
          "DialogueText": "Kaba!",
          "AudioPath": "assets/tr-TR/Lewis/124.ogg"
        },
        {
          "DialogueFrom": "Event:ManorHouse/2123243/e 2111194_alt",
          "DialogueText": "Aman tanrım!",
          "AudioPath": "assets/tr-TR/Lewis/125.ogg"
        },
        {
          "DialogueFrom": "Event:ManorHouse/2123243/e 2111194_alt_1",
          "DialogueText": "Neden olmasın...",
          "AudioPath": "assets/tr-TR/Lewis/126.ogg"
        },
        {
          "DialogueFrom": "Event:ManorHouse/prizeTicketIntro/n completedFirstBillboardQuest",
          "DialogueText": "Ah, selam .",
          "AudioPath": "assets/tr-TR/Lewis/127.ogg"
        },
        {
          "DialogueFrom": "Event:ManorHouse/prizeTicketIntro/n completedFirstBillboardQuest_1",
          "DialogueText": "Şu zaman makinesine birkaç ödül yerleştiriyordum...",
          "AudioPath": "assets/tr-TR/Lewis/128.ogg"
        },
        {
          "DialogueFrom": "Event:ManorHouse/prizeTicketIntro/n completedFirstBillboardQuest_2",
          "DialogueText": "Sen de dahil kasaba halkına iyi niyet aşılamak için kendi bulduğum bir fikir...",
          "AudioPath": "assets/tr-TR/Lewis/129.ogg"
        },
        {
          "DialogueFrom": "Event:ManorHouse/prizeTicketIntro/n completedFirstBillboardQuest_2_1",
          "DialogueText": "Oldukça basit... Kasaba halkına yardım ederken bazen Ödül Bileti elde edeceksin. Bunları ödüle dönüştürebilirsin.",
          "AudioPath": "assets/tr-TR/Lewis/130.ogg"
        },
        {
          "DialogueFrom": "Event:ManorHouse/prizeTicketIntro/n completedFirstBillboardQuest_2_2",
          "DialogueText": "Burada bazı özel şeyler de var!",
          "AudioPath": "assets/tr-TR/Lewis/131.ogg"
        },
        {
          "DialogueFrom": "Event:ManorHouse/prizeTicketIntro/n completedFirstBillboardQuest_3",
          "DialogueText": "Tek endişem, insanların ahbaplarına yardımcı olmanın gerçek tutkusu yerine sadece biletlerin peşinde olmaları...",
          "AudioPath": "assets/tr-TR/Lewis/132.ogg"
        },
        {
          "DialogueFrom": "Event:ManorHouse/prizeTicketIntro/n completedFirstBillboardQuest_4",
          "DialogueText": "Her neyse... Kasabaki 'Yardım Aranıyor' panosunu takip et. Böylece daha fazla bilet bulabilirsin.",
          "AudioPath": "assets/tr-TR/Lewis/133.ogg"
        },
        {
          "DialogueFrom": "Event:ManorHouse/prizeTicketIntro/n completedFirstBillboardQuest_4_1",
          "DialogueText": "Bol şans.",
          "AudioPath": "assets/tr-TR/Lewis/134.ogg"
        },
        {
          "DialogueFrom": "Event:ManorHouse/prizeTicketIntro/n completedFirstBillboardQuest_implied",
          "DialogueText": "Öyle mi? Bunu duyduğuma sevindim!",
          "AudioPath": "assets/tr-TR/Lewis/135.ogg"
        },
        {
          "DialogueFrom": "Event:ManorHouse/prizeTicketIntro/n completedFirstBillboardQuest_implied_1",
          "DialogueText": "Anlıyorum!",
          "AudioPath": "assets/tr-TR/Lewis/136.ogg"
        },
        {
          "DialogueFrom": "Event:ManorHouse/prizeTicketIntro/n completedFirstBillboardQuest_implied_1_1",
          "DialogueText": "Eh... Bu, duymayı umduğum şey değildi fakat dürüstlüğün için teşekkür ederim.",
          "AudioPath": "assets/tr-TR/Lewis/137.ogg"
        },
        {
          "DialogueFrom": "Event:Saloon/3206194/n gusGiantOmelet_alt",
          "DialogueText": "Imm..",
          "AudioPath": "assets/tr-TR/Lewis/138.ogg"
        },
        {
          "DialogueFrom": "Event:Town/15389722/j 57",
          "DialogueText": "Merhaba . Tam zamanında geldin.",
          "AudioPath": "assets/tr-TR/Lewis/139.ogg"
        },
        {
          "DialogueFrom": "Event:Town/15389722/j 57_1",
          "DialogueText": "Bu bizim yeni 'Özel Sipariş' panomuz.",
          "AudioPath": "assets/tr-TR/Lewis/140.ogg"
        },
        {
          "DialogueFrom": "Event:Town/15389722/j 57_1_1",
          "DialogueText": "Robin'le birlikte yaptık.",
          "AudioPath": "assets/tr-TR/Lewis/141.ogg"
        },
        {
          "DialogueFrom": "Event:Town/15389722/j 57_2",
          "DialogueText": "*öksürür*... Boş ver sen onu.",
          "AudioPath": "assets/tr-TR/Lewis/142.ogg"
        },
        {
          "DialogueFrom": "Event:Town/15389722/j 57_3",
          "DialogueText": "Gel sana durumu açıklayayım...",
          "AudioPath": "assets/tr-TR/Lewis/143.ogg"
        },
        {
          "DialogueFrom": "Event:Town/15389722/j 57_4",
          "DialogueText": "çiftliği tekrardan açıldığından kasabamızda işler tıkırında gidiyor.",
          "AudioPath": "assets/tr-TR/Lewis/144.ogg"
        },
        {
          "DialogueFrom": "Event:Town/15389722/j 57_4_1",
          "DialogueText": "Bölge halkının bir kısmı, çiftlikte üretilen ürünlerin kendi işletmeleri veya kişisel çalışmaları için kaynak olarak kullanılabilmesini talep ediyordu.",
          "AudioPath": "assets/tr-TR/Lewis/145.ogg"
        },
        {
          "DialogueFrom": "Event:Town/15389722/j 57_5",
          "DialogueText": "Ben ve Robin de bu 'Özel Sipariş' panosu fikriyle çıkageldik. İnsanlar çok daha büyük çaplı ilanlarını Pierre'in dükkanının önü yerine buraya asacak.",
          "AudioPath": "assets/tr-TR/Lewis/146.ogg"
        },
        {
          "DialogueFrom": "Event:Town/15389722/j 57_alt",
          "DialogueText": "*inler*",
          "AudioPath": "assets/tr-TR/Lewis/147.ogg"
        },
        {
          "DialogueFrom": "Event:Town/191393/Hn ccFishTank/Hn ccBulletin/Hn ccPantry/Hn ccVault/Hn ccBoilerRoom/Hn ccCraftsRoom/Hl jojaFishTank/Hl jojaPantry/Hl jojaVault/Hl jojaBoilerRoom/Hl jojaCraftsRoom/Hl JojaMember/w sunny/H",
          "DialogueText": "Nasıl yaptığını bilmiyorum, ... ama halkevi hiç bu kadar iyi görünmemişti!",
          "AudioPath": "assets/tr-TR/Lewis/148.ogg"
        },
        {
          "DialogueFrom": "Event:Town/191393/Hn ccFishTank/Hn ccBulletin/Hn ccPantry/Hn ccVault/Hn ccBoilerRoom/Hn ccCraftsRoom/Hl jojaFishTank/Hl jojaPantry/Hl jojaVault/Hl jojaBoilerRoom/Hl jojaCraftsRoom/Hl JojaMember/w sunny/H_1",
          "DialogueText": "Pelikan Kasabası'na harika bir hizmette bulundun. Kasabadaki herkes minnettar.",
          "AudioPath": "assets/tr-TR/Lewis/149.ogg"
        },
        {
          "DialogueFrom": "Event:Town/191393/Hn ccFishTank/Hn ccBulletin/Hn ccPantry/Hn ccVault/Hn ccBoilerRoom/Hn ccCraftsRoom/Hl jojaFishTank/Hl jojaPantry/Hl jojaVault/Hl jojaBoilerRoom/Hl jojaCraftsRoom/Hl JojaMember/w sunny/H_1",
          "DialogueText": "'Teşekkür ederim' demek için sana bu kasabanın en büyük onurunu sunmak istiyorum... Yıldızçiyi Kahramanı Ödülü. Bunu hak ettin!",
          "AudioPath": "assets/tr-TR/Lewis/150.ogg"
        },
        {
          "DialogueFrom": "Event:Town/191393/Hn ccFishTank/Hn ccBulletin/Hn ccPantry/Hn ccVault/Hn ccBoilerRoom/Hn ccCraftsRoom/Hl jojaFishTank/Hl jojaPantry/Hl jojaVault/Hl jojaBoilerRoom/Hl jojaCraftsRoom/Hl JojaMember/w sunny/H_alt",
          "DialogueText": "SES: *homurdanır*",
          "AudioPath": "assets/tr-TR/Lewis/151.ogg"
        },
        {
          "DialogueFrom": "Event:Town/191393/Hn ccFishTank/Hn ccBulletin/Hn ccPantry/Hn ccVault/Hn ccBoilerRoom/Hn ccCraftsRoom/Hl jojaFishTank/Hl jojaPantry/Hl jojaVault/Hl jojaBoilerRoom/Hl jojaCraftsRoom/Hl JojaMember/w sunny/H_alt_1",
          "DialogueText": "Kim var orada?",
          "AudioPath": "assets/tr-TR/Lewis/152.ogg"
        },
        {
          "DialogueFrom": "Event:Town/191393/Hn ccFishTank/Hn ccBulletin/Hn ccPantry/Hn ccVault/Hn ccBoilerRoom/Hn ccCraftsRoom/Hl jojaFishTank/Hl jojaPantry/Hl jojaVault/Hl jojaBoilerRoom/Hl jojaCraftsRoom/Hl JojaMember/w sunny/H_alt_2",
          "DialogueText": "Ha, Morris.",
          "AudioPath": "assets/tr-TR/Lewis/153.ogg"
        },
        {
          "DialogueFrom": "Event:Town/45/f Sam 1500/t 1200 1600/w sunny",
          "DialogueText": "Hey! Ne yaptığını sanıyorsun? Burası özel mülk!",
          "AudioPath": "assets/tr-TR/Lewis/154.ogg"
        },
        {
          "DialogueFrom": "Event:Town/45/f Sam 1500/t 1200 1600/w sunny_1",
          "DialogueText": "*iç çeker*... Ah, siz gençlik yok musunuz... Bazen bu kasaba kaderine mi mahkum edilmiş diye düşünemeden edemiyorum.",
          "AudioPath": "assets/tr-TR/Lewis/155.ogg"
        },
        {
          "DialogueFrom": "Event:Town/45/f Sam 1500/t 1200 1600/w sunny_2",
          "DialogueText": "Ne olduğunu gördün, . Bunun hakkında ne diyeceksin?",
          "AudioPath": "assets/tr-TR/Lewis/156.ogg"
        },
        {
          "DialogueFrom": "Event:Town/45/f Sam 1500/t 1200 1600/w sunny_alt",
          "DialogueText": "Sam!",
          "AudioPath": "assets/tr-TR/Lewis/157.ogg"
        },
        {
          "DialogueFrom": "Event:Town/45/f Sam 1500/t 1200 1600/w sunny_implied",
          "DialogueText": "Sam'i suçlamayın. Onun kaykaya binebileceği başka bir yer yok!#Ben bu işe karışmıyorum.",
          "AudioPath": "assets/tr-TR/Lewis/158.ogg"
        },
        {
          "DialogueFrom": "Event:Town/45/f Sam 1500/t 1200 1600/w sunny_implied_1",
          "DialogueText": "Peki! Bir daha asla kaykaya binmeyeceğim! Mutlu musunuz?~Aynen öyle! Kasabada bir park olsaydı, orada kaykay yapardım ve herkes mutlu olurdu.~Hım. Tamam.",
          "AudioPath": "assets/tr-TR/Lewis/159.ogg"
        },
        {
          "DialogueFrom": "Event:Town/45/f Sam 1500/t 1200 1600/w sunny_implied_2",
          "DialogueText": "Sıkıntılı davranıyorsun, Sam. Kasabanın etrafında kaykay binmekle ilgili hiçbir problemim yok, sadece zarar vermemeye çalış! Bu kadar basit.~Hım. Daha olgun biri olduğunu sanmıştım, .~Bu seferlik kaymana izin vereceğim, Sam. Ama seni artık bunu yaparken görmek istemiyorum.",
          "AudioPath": "assets/tr-TR/Lewis/160.ogg"
        },
        {
          "DialogueFrom": "Event:Town/45/f Sam 1500/t 1200 1600/w sunny_implied_3",
          "DialogueText": "Anladın mı?~Sana bağırdığım için özür dilerim. Lütfen sadece gelecekte bir şeylere zarar vermemeye çalış. Olur mu?~Tamam mı?",
          "AudioPath": "assets/tr-TR/Lewis/161.ogg"
        },
        {
          "DialogueFrom": "Event:Town/53/e 55/t 1500 1700",
          "DialogueText": "Seninle gurur duyuyorum Leah! Böyle olaylar gerçekten küçük kasabamıza hayat veriyor!",
          "AudioPath": "assets/tr-TR/Lewis/162.ogg"
        },
        {
          "DialogueFrom": "Event:Town/53/e 55/t 1500 1700_1",
          "DialogueText": "Hadi şimdi bu harika sanat eserlerine fiyat biçmeye başlayalım... Evinize güzel bir görünüm katabilirler!",
          "AudioPath": "assets/tr-TR/Lewis/163.ogg"
        },
        {
          "DialogueFrom": "Event:Town/53/e 55/t 1500 1700_1_1",
          "DialogueText": "Pembe olan için 5000g mi duyuyorum?",
          "AudioPath": "assets/tr-TR/Lewis/164.ogg"
        },
        {
          "DialogueFrom": "Event:Town/53/e 55/t 1500 1700_implied",
          "DialogueText": "Vay be! Yoruldum.",
          "AudioPath": "assets/tr-TR/Lewis/165.ogg"
        },
        {
          "DialogueFrom": "Event:Town/53/e 55/t 1500 1700_implied_1",
          "DialogueText": "Gösteri tam anlamıyla başarılıydı, değil mi?",
          "AudioPath": "assets/tr-TR/Lewis/166.ogg"
        },
        {
          "DialogueFrom": "Event:Town/611439/j 4/t 800 1300/w sunny/a 0 54/H",
          "DialogueText": "Ah, selam.",
          "AudioPath": "assets/tr-TR/Lewis/167.ogg"
        },
        {
          "DialogueFrom": "Event:Town/611439/j 4/t 800 1300/w sunny/a 0 54/H_1",
          "DialogueText": "Ne kadar da göze batıyor...",
          "AudioPath": "assets/tr-TR/Lewis/168.ogg"
        },
        {
          "DialogueFrom": "Event:Town/611439/j 4/t 800 1300/w sunny/a 0 54/H_10",
          "DialogueText": "Ne?",
          "AudioPath": "assets/tr-TR/Lewis/169.ogg"
        },
        {
          "DialogueFrom": "Event:Town/611439/j 4/t 800 1300/w sunny/a 0 54/H_11",
          "DialogueText": "Sorun nedir? İyi misin?",
          "AudioPath": "assets/tr-TR/Lewis/170.ogg"
        },
        {
          "DialogueFrom": "Event:Town/611439/j 4/t 800 1300/w sunny/a 0 54/H_12",
          "DialogueText": "Bir şey mi gördün? Hım... Burası kesin sıçanlarla doludur.",
          "AudioPath": "assets/tr-TR/Lewis/171.ogg"
        },
        {
          "DialogueFrom": "Event:Town/611439/j 4/t 800 1300/w sunny/a 0 54/H_13",
          "DialogueText": "Beni endişelendiriyorsun, ...",
          "AudioPath": "assets/tr-TR/Lewis/172.ogg"
        },
        {
          "DialogueFrom": "Event:Town/611439/j 4/t 800 1300/w sunny/a 0 54/H_14",
          "DialogueText": "Şey, sanırım eve gideceğim, acıkmaya başladım.",
          "AudioPath": "assets/tr-TR/Lewis/173.ogg"
        },
        {
          "DialogueFrom": "Event:Town/611439/j 4/t 800 1300/w sunny/a 0 54/H_15",
          "DialogueText": "Bundan sonra burayı açık tutacağım... Belki fazladan zamanın olursa o sıçanları yakalamaya yardım edersin.",
          "AudioPath": "assets/tr-TR/Lewis/174.ogg"
        },
        {
          "DialogueFrom": "Event:Town/611439/j 4/t 800 1300/w sunny/a 0 54/H_2",
          "DialogueText": "Burası, Pelikan Kasabası Halkevi... Ya da ondan geriye ne kaldıysa işte.",
          "AudioPath": "assets/tr-TR/Lewis/175.ogg"
        },
        {
          "DialogueFrom": "Event:Town/611439/j 4/t 800 1300/w sunny/a 0 54/H_3",
          "DialogueText": "Eskiden kasabanın eğlence ve toplanma merkeziydi.",
          "AudioPath": "assets/tr-TR/Lewis/176.ogg"
        },
        {
          "DialogueFrom": "Event:Town/611439/j 4/t 800 1300/w sunny/a 0 54/H_4",
          "DialogueText": "Bir de şimdiki haline bak... utanç verici.",
          "AudioPath": "assets/tr-TR/Lewis/177.ogg"
        },
        {
          "DialogueFrom": "Event:Town/611439/j 4/t 800 1300/w sunny/a 0 54/H_4_1",
          "DialogueText": "Bu günlerde gençlik, televizyonun önünde oturup toplumla ilişki kurmaktan kaçınıyor.",
          "AudioPath": "assets/tr-TR/Lewis/178.ogg"
        },
        {
          "DialogueFrom": "Event:Town/611439/j 4/t 800 1300/w sunny/a 0 54/H_5",
          "DialogueText": "Bakar mısın, yaşlı dayılar gibi konuşuyorum.",
          "AudioPath": "assets/tr-TR/Lewis/179.ogg"
        },
        {
          "DialogueFrom": "Event:Town/611439/j 4/t 800 1300/w sunny/a 0 54/H_6",
          "DialogueText": "Joja Şirketi toprağımı satmam için beni zorluyor ki burayı depoya çevirebilsinler...",
          "AudioPath": "assets/tr-TR/Lewis/180.ogg"
        },
        {
          "DialogueFrom": "Event:Town/611439/j 4/t 800 1300/w sunny/a 0 54/H_6_1",
          "DialogueText": "Gelecek paranın Pelikan Kasabası'na faydası dokunabilir. Yine de burayı satmama engel olan bir şey var... Sanırım yaşlandıkça geçmişten kalan şeylere iyice bağlanıyorum... Neyse yav.",
          "AudioPath": "assets/tr-TR/Lewis/181.ogg"
        },
        {
          "DialogueFrom": "Event:Town/611439/j 4/t 800 1300/w sunny/a 0 54/H_6_2",
          "DialogueText": "Eğer bir başkası daha Joja Şirketi Üyeliği alırsa, araziyi satacağım.",
          "AudioPath": "assets/tr-TR/Lewis/182.ogg"
        },
        {
          "DialogueFrom": "Event:Town/611439/j 4/t 800 1300/w sunny/a 0 54/H_7",
          "DialogueText": "*iç çeker* ...Gel, içeri geçelim...",
          "AudioPath": "assets/tr-TR/Lewis/183.ogg"
        },
        {
          "DialogueFrom": "Event:Town/611439/j 4/t 800 1300/w sunny/a 0 54/H_8",
          "DialogueText": "Hım. Bu da ne?..",
          "AudioPath": "assets/tr-TR/Lewis/184.ogg"
        },
        {
          "DialogueFrom": "Event:Town/611439/j 4/t 800 1300/w sunny/a 0 54/H_8_1",
          "DialogueText": "Sanırım Vincent ve Jas burada oyun oynuyormuş.",
          "AudioPath": "assets/tr-TR/Lewis/185.ogg"
        },
        {
          "DialogueFrom": "Event:Town/611439/j 4/t 800 1300/w sunny/a 0 54/H_9",
          "DialogueText": "Burası hatırladığımdan daha harap halde.",
          "AudioPath": "assets/tr-TR/Lewis/186.ogg"
        },
        {
          "DialogueFrom": "Event:Town/611439/j 4/t 800 1300/w sunny/a 0 54/H_alt",
          "DialogueText": "Garip...",
          "AudioPath": "assets/tr-TR/Lewis/187.ogg"
        },
        {
          "DialogueFrom": "Event:Town/611439/j 4/t 800 1300/w sunny/a 0 54/H_alt_1",
          "DialogueText": "Daha sonra buraya dönüp dikkatlice incelemem gerekecek.",
          "AudioPath": "assets/tr-TR/Lewis/188.ogg"
        },
        {
          "DialogueFrom": "Event:Town/639373/f Lewis 1500/f Marnie 1500/t 1900 2300/w sunny",
          "DialogueText": "Marnie... yapamayız. Eğer bu duyulursa kasabada benim için ne derler? İşimden olursam ne olacak?",
          "AudioPath": "assets/tr-TR/Lewis/189.ogg"
        },
        {
          "DialogueFrom": "Event:Town/639373/f Lewis 1500/f Marnie 1500/t 1900 2300/w sunny_1",
          "DialogueText": "Anlıyorsun... Değil mi?",
          "AudioPath": "assets/tr-TR/Lewis/190.ogg"
        },
        {
          "DialogueFrom": "Event:Town/639373/f Lewis 1500/f Marnie 1500/t 1900 2300/w sunny_2",
          "DialogueText": "200 null 200 50 event_secret1 201 -100 event_secret2#Evet... ve bunu herkese söyleyeceğim!",
          "AudioPath": "assets/tr-TR/Lewis/191.ogg"
        },
        {
          "DialogueFrom": "ExtraDialogue",
          "DialogueText": "Vay be. Şu manzaraya bakar mısın...",
          "AudioPath": "assets/tr-TR/Lewis/192.ogg"
        },
        {
          "DialogueFrom": "ExtraDialogue_1",
          "DialogueText": ", biliyor musun... Yıllardır bu kasabanın belediye başkanlığını yapıyorum.",
          "AudioPath": "assets/tr-TR/Lewis/193.ogg"
        },
        {
          "DialogueFrom": "ExtraDialogue_1_1",
          "DialogueText": "Bir sürü insan gelip gitti. Hepimiz hem zorluk hem de bolluk dönemleri geçirdik.",
          "AudioPath": "assets/tr-TR/Lewis/194.ogg"
        },
        {
          "DialogueFrom": "ExtraDialogue_2",
          "DialogueText": "Ama şunu söylemeliyim ki, başkanlık yaptığım bunca senede Çiftliği'nin senin gelişinle yeniden doğması kadar beni gururlandıran başka hiçbir şey olmadı.",
          "AudioPath": "assets/tr-TR/Lewis/195.ogg"
        },
        {
          "DialogueFrom": "ExtraDialogue_2_1",
          "DialogueText": "Çiftliği büyükbabanın en çılgın hayallerinin de ötesine taşıdın.",
          "AudioPath": "assets/tr-TR/Lewis/196.ogg"
        },
        {
          "DialogueFrom": "ExtraDialogue_2_2",
          "DialogueText": "Bu sırada vadimizi de sonsuza dek değiştirdin.",
          "AudioPath": "assets/tr-TR/Lewis/197.ogg"
        },
        {
          "DialogueFrom": "ExtraDialogue_3",
          "DialogueText": ", belki farkında olmayabilirsin ama bu kasabayı çok önemsiyorum.",
          "AudioPath": "assets/tr-TR/Lewis/198.ogg"
        },
        {
          "DialogueFrom": "ExtraDialogue_3_1",
          "DialogueText": "yıl önce vadimizin geleceği konusunda derinden endişeliydim.",
          "AudioPath": "assets/tr-TR/Lewis/199.ogg"
        },
        {
          "DialogueFrom": "ExtraDialogue_3_2",
          "DialogueText": "Şimdi ise içim o kadar rahat ki.",
          "AudioPath": "assets/tr-TR/Lewis/200.ogg"
        },
        {
          "DialogueFrom": "ExtraDialogue_3_3",
          "DialogueText": "Mütevazı bir çiftçinin her şeyi böylesine değiştireceğini kim bilebilirdi??",
          "AudioPath": "assets/tr-TR/Lewis/201.ogg"
        },
        {
          "DialogueFrom": "ExtraDialogue_3_4",
          "DialogueText": "...Teşekkür ederim.",
          "AudioPath": "assets/tr-TR/Lewis/202.ogg"
        },
        {
          "DialogueFrom": "Festival/fall16",
          "DialogueText": "Evet . Bugün büyük gün... 'Yıldızçiyi Vadisi Şöleni' yılın en önemli etkinliğidir.Eğer çiftlik sergisi açmak istersen diye stantlardan birini boş bıraktım. Sergiyi kurmayı bitirdiğinde bana haber ver ki puanlamaya geçelim.",
          "AudioPath": "assets/tr-TR/Lewis/203.ogg"
        },
        {
          "DialogueFrom": "Festival/fall16_1",
          "DialogueText": "Merhaba ! 'Yıldızçiyi Vadisi Şöleni' nihayet geldi, kalabalık her dakika artıyor.Geçen yıl olduğu gibi senin için boş bir sergi alanı hazırladım. Değerlendirilmeye başlamaya hazır olduğunda benimle konuş.",
          "AudioPath": "assets/tr-TR/Lewis/204.ogg"
        },
        {
          "DialogueFrom": "Festival/fall27",
          "DialogueText": "İyi akşamlar . Perili labirentten geçtin mi? Bayağı ürkütücü.Şuradaki garip adam yaşadığı o kuleyi tek başına yapmıştı. İnşaata kimseyi yaklaştırmazdı.",
          "AudioPath": "assets/tr-TR/Lewis/205.ogg"
        },
        {
          "DialogueFrom": "Festival/fall27_1",
          "DialogueText": "İyi akşamlar . Ormanda yaşayan münzevimiz, gizlice inşa ettiği bu labirenti bir kez daha bize bahşetti.Bu seferki daha büyükmüş. Gireceksen sana bol şans diliyorum...",
          "AudioPath": "assets/tr-TR/Lewis/206.ogg"
        },
        {
          "DialogueFrom": "Festival/spring13",
          "DialogueText": "Vay canına! Tüm şu yumurtalara baksana.Siz de bu kadar çok üreseniz, herhalde Mücevher Denizi'nin bu tarafındaki en çok nüfusa sahip kasaba bizimki olurdu! *güler*",
          "AudioPath": "assets/tr-TR/Lewis/207.ogg"
        },
        {
          "DialogueFrom": "Festival/spring13_1",
          "DialogueText": "Şimdi de, bu yılki Yumurta Avı'nın kazananı...",
          "AudioPath": "assets/tr-TR/Lewis/208.ogg"
        },
        {
          "DialogueFrom": "Festival/spring13_10",
          "DialogueText": "Vay be, tüm şu yumurtalara bak!Keşke siz çocukları çöpleri bu şekilde toplamaya ikna edebilseydim, Mücevher Denizi'nin ötesindeki en temiz kasaba bizimki olurdu! *güler*",
          "AudioPath": "assets/tr-TR/Lewis/209.ogg"
        },
        {
          "DialogueFrom": "Festival/spring13_11",
          "DialogueText": "Şimdi de bu yılki yumurta avının kazananı...",
          "AudioPath": "assets/tr-TR/Lewis/210.ogg"
        },
        {
          "DialogueFrom": "Festival/spring13_12",
          "DialogueText": "İşte ödülün! Tadını çıkar.",
          "AudioPath": "assets/tr-TR/Lewis/211.ogg"
        },
        {
          "DialogueFrom": "Festival/spring13_13",
          "DialogueText": "Eh, bu yılki Yumurta Şöleni de bu kadardı. Katılan herkese teşekkürler!",
          "AudioPath": "assets/tr-TR/Lewis/212.ogg"
        },
        {
          "DialogueFrom": "Festival/spring13_14",
          "DialogueText": "Bugünkü etkinliklerin en önemlisi olan Geleneksel Bahar Yumurta Avı'nın zamanı geldi!",
          "AudioPath": "assets/tr-TR/Lewis/213.ogg"
        },
        {
          "DialogueFrom": "Festival/spring13_15",
          "DialogueText": "Sakin olun çocuklar. Bu özel ödülü kazanmak için tüm enerjinize ihtiyacınız olacak.",
          "AudioPath": "assets/tr-TR/Lewis/214.ogg"
        },
        {
          "DialogueFrom": "Festival/spring13_16",
          "DialogueText": "Şimdi... Herkes hazır mı?",
          "AudioPath": "assets/tr-TR/Lewis/215.ogg"
        },
        {
          "DialogueFrom": "Festival/spring13_17",
          "DialogueText": "Yumurta avı başlasın!",
          "AudioPath": "assets/tr-TR/Lewis/216.ogg"
        },
        {
          "DialogueFrom": "Festival/spring13_18",
          "DialogueText": "Takılıyor musun, ?",
          "AudioPath": "assets/tr-TR/Lewis/217.ogg"
        },
        {
          "DialogueFrom": "Festival/spring13_2",
          "DialogueText": "İşte ödülün. Tadını çıkar.",
          "AudioPath": "assets/tr-TR/Lewis/218.ogg"
        },
        {
          "DialogueFrom": "Festival/spring13_3",
          "DialogueText": "Bu yılki Yumurta Şöleni bu kadardı. Geldiğiniz için teşekkür ederim, millet!",
          "AudioPath": "assets/tr-TR/Lewis/219.ogg"
        },
        {
          "DialogueFrom": "Festival/spring13_4",
          "DialogueText": "İşte ödülün, Abigail. Tadını çıkar!",
          "AudioPath": "assets/tr-TR/Lewis/220.ogg"
        },
        {
          "DialogueFrom": "Festival/spring13_6",
          "DialogueText": "Sıra geldi bugünkü şölenin asıl olayına... Yıllık Bahar Yumurtası Avı zamanı geldi!",
          "AudioPath": "assets/tr-TR/Lewis/221.ogg"
        },
        {
          "DialogueFrom": "Festival/spring13_7",
          "DialogueText": "Sakin olun çocuklar. Tüm yumurtaları bulup özel ödülümüzü eve götürebilmeniz için o harcadığınız enerjilere ihtiyacınız olacak.",
          "AudioPath": "assets/tr-TR/Lewis/222.ogg"
        },
        {
          "DialogueFrom": "Festival/spring13_8",
          "DialogueText": "Pekâlâ... Herkes hazır mı?",
          "AudioPath": "assets/tr-TR/Lewis/223.ogg"
        },
        {
          "DialogueFrom": "Festival/spring13_9",
          "DialogueText": "Av başlasın o zaman!",
          "AudioPath": "assets/tr-TR/Lewis/224.ogg"
        },
        {
          "DialogueFrom": "Festival/spring24",
          "DialogueText": "Eğer diğer gençlerle dans etmek istiyorsan bir eş bulmalısın.",
          "AudioPath": "assets/tr-TR/Lewis/225.ogg"
        },
        {
          "DialogueFrom": "Festival/spring24_1",
          "DialogueText": "Tünaydın . Bugünkü etkinlik için hava daha mükemmel olamazdı.Töreni başlatmaya hazır olduğunda yanıma gel.",
          "AudioPath": "assets/tr-TR/Lewis/226.ogg"
        },
        {
          "DialogueFrom": "Festival/summer11",
          "DialogueText": "Pekâlâ millet. Yine bir karışık çorba seremonisine başlayacağız.Hepinizin elindeki en kaliteli ürünü çorbaya katacağına güveniyorum. Vali'nin vadiye ziyaretinden pişmanlık duymasını istemeyiz!",
          "AudioPath": "assets/tr-TR/Lewis/227.ogg"
        },
        {
          "DialogueFrom": "Festival/summer11_1",
          "DialogueText": "Buyrun... Vali Bey. Çorbamızın tadına bakma onurunu bizlere layık görür müydünüz acaba?",
          "AudioPath": "assets/tr-TR/Lewis/228.ogg"
        },
        {
          "DialogueFrom": "Festival/summer11_10",
          "DialogueText": "Şimdi... Kim çorba istiyor?",
          "AudioPath": "assets/tr-TR/Lewis/229.ogg"
        },
        {
          "DialogueFrom": "Festival/summer11_11",
          "DialogueText": "Haklısınız... Pek de orijinal değil. Kötü de değil gerçi.",
          "AudioPath": "assets/tr-TR/Lewis/230.ogg"
        },
        {
          "DialogueFrom": "Festival/summer11_12",
          "DialogueText": "Evet... Kimler çorba istiyor?",
          "AudioPath": "assets/tr-TR/Lewis/231.ogg"
        },
        {
          "DialogueFrom": "Festival/summer11_13",
          "DialogueText": "Öğk. Birisi kötü kalitedeki bir malzeme ile çorbayı mahvetmiş.",
          "AudioPath": "assets/tr-TR/Lewis/232.ogg"
        },
        {
          "DialogueFrom": "Festival/summer11_14",
          "DialogueText": "Evet... İsteyen var mı?",
          "AudioPath": "assets/tr-TR/Lewis/233.ogg"
        },
        {
          "DialogueFrom": "Festival/summer11_15",
          "DialogueText": "Aferin millet... Vali'nin bayılmasına yol açan kötü malzemeyi kim koyduysa, ona aferin! Utanç içerisindeyim.",
          "AudioPath": "assets/tr-TR/Lewis/234.ogg"
        },
        {
          "DialogueFrom": "Festival/summer11_16",
          "DialogueText": "Evlere dağılın. Şölen sona erdi.",
          "AudioPath": "assets/tr-TR/Lewis/235.ogg"
        },
        {
          "DialogueFrom": "Festival/summer11_17",
          "DialogueText": "Merhabalar, hoş geldiniz! Ortak çorba töreninin başladığını duyurmaktan mutluluk duyuyorum.Umarım herkes üst kalite malzemelerle katkıda bulunmuştur! Vali Beyde iyi bir izlenim bırakmak istiyoruz.",
          "AudioPath": "assets/tr-TR/Lewis/236.ogg"
        },
        {
          "DialogueFrom": "Festival/summer11_18",
          "DialogueText": "Vali Bey, ilk tadımı yaparak bizi onurlandırır mıydınız?",
          "AudioPath": "assets/tr-TR/Lewis/237.ogg"
        },
        {
          "DialogueFrom": "Festival/summer11_19",
          "DialogueText": "Canlan! Vali yıllık ziyareti için aramızda.Eğer karışık çorba için bir şey getirdiysen kazana eklemeyi unutma.",
          "AudioPath": "assets/tr-TR/Lewis/238.ogg"
        },
        {
          "DialogueFrom": "Festival/summer11_2",
          "DialogueText": "Bu iş kimin başının altından çıktıysa onu kınıyorum. Özel eşyalarım nasıl böyle bir amaç için kullanılır?Mükemmel bir çorbayı mahvetmek... affedilemez! Daha önce bu topluluktan bu kadar utanmamıştım... Gerçekten iğrenç.",
          "AudioPath": "assets/tr-TR/Lewis/239.ogg"
        },
        {
          "DialogueFrom": "Festival/summer11_20",
          "DialogueText": "Vali Bey, bugünün seçkin konuğu! Hepinizin saygıda kusur etmemenizi bekliyorum.Ortak yemeğe katılacaklar, malzemelerinizi çorba kazanına ekleyin.",
          "AudioPath": "assets/tr-TR/Lewis/240.ogg"
        },
        {
          "DialogueFrom": "Festival/summer11_3",
          "DialogueText": "Evlerinize dağılın. Şölen sona erdi!",
          "AudioPath": "assets/tr-TR/Lewis/241.ogg"
        },
        {
          "DialogueFrom": "Festival/summer11_4",
          "DialogueText": "Haklısınız... Biraz tatsız olmuş.",
          "AudioPath": "assets/tr-TR/Lewis/242.ogg"
        },
        {
          "DialogueFrom": "Festival/summer11_5",
          "DialogueText": "Bu yıl aramızda olduğunuz için teşekkür ederiz, Vali Bey. Çorbanın sıradan oluşunu lütfen mazur görün.",
          "AudioPath": "assets/tr-TR/Lewis/243.ogg"
        },
        {
          "DialogueFrom": "Festival/summer11_7",
          "DialogueText": "Gerçekten... çok lezzetli!",
          "AudioPath": "assets/tr-TR/Lewis/244.ogg"
        },
        {
          "DialogueFrom": "Festival/summer11_8",
          "DialogueText": "Harika iş çıkardınız millet! Şimdi... Başka kim tadına bakmak istiyor?",
          "AudioPath": "assets/tr-TR/Lewis/245.ogg"
        },
        {
          "DialogueFrom": "Festival/summer11_9",
          "DialogueText": "Ah... Nefis. Bugün harika iş çıkardınız.",
          "AudioPath": "assets/tr-TR/Lewis/246.ogg"
        },
        {
          "DialogueFrom": "Festival/summer28",
          "DialogueText": "İyi akşamlar . Ayışığı denizanaları yaklaşıyor... Uzakta parıldayan bir tane gördüm bile.Mumlu kayığı denize bıraktığımız zaman gelip bize merhaba diyecekler.",
          "AudioPath": "assets/tr-TR/Lewis/247.ogg"
        },
        {
          "DialogueFrom": "Festival/summer28_1",
          "DialogueText": "Merhaba . Akşam çöktükçe Ayışığı Denizanaları kıyıya yaklaşır.Mumlu kayığı yola çıkarır çıkarmaz iskelelerin etrafında toplanırlar.",
          "AudioPath": "assets/tr-TR/Lewis/248.ogg"
        },
        {
          "DialogueFrom": "Festival/winter25",
          "DialogueText": "Bugün güzel geçen yılımız için şükretme zamanı. Kaygılarını unut ve rahatla!",
          "AudioPath": "assets/tr-TR/Lewis/249.ogg"
        },
        {
          "DialogueFrom": "Festival/winter25_1",
          "DialogueText": "Kış Yıldızı Şöleni kutlu olsun .Bugün; rahatlamak, iyi dostlukların keyfini çıkarmak ve sahip olduğumuz her şey için şükran duymak için.",
          "AudioPath": "assets/tr-TR/Lewis/250.ogg"
        },
        {
          "DialogueFrom": "Festival/winter8",
          "DialogueText": "Pekâlâ millet. Hadi bu yılın buzda balık tutma yarışmasını başlatalım.",
          "AudioPath": "assets/tr-TR/Lewis/251.ogg"
        },
        {
          "DialogueFrom": "Festival/winter8_1",
          "DialogueText": "Yarışmacılar, göreviniz sizlere verilen oltalar ile en fazla balığı yakalamak olacak.Balıklarınızı buz deliklerinden yakalamanız gerekiyor.",
          "AudioPath": "assets/tr-TR/Lewis/252.ogg"
        },
        {
          "DialogueFrom": "Festival/winter8_10",
          "DialogueText": "Bu seneki Buz Şöleni burada sona eriyor. Geldiğiniz için teşekkürler, millet!Artık şu zavallı balıkları salalım...",
          "AudioPath": "assets/tr-TR/Lewis/253.ogg"
        },
        {
          "DialogueFrom": "Festival/winter8_11",
          "DialogueText": "Buz Şöleni'ne hoş geldin!Bugünün ilgi çekici etkinliği, buzda balık tutma yarışması elbette. 'Donmuş bir göl' oluşturduk ve içini balıklarla doldurduk.Yarışmaya katılmak için bana hazır olduğunu söylemen yeterli.",
          "AudioPath": "assets/tr-TR/Lewis/254.ogg"
        },
        {
          "DialogueFrom": "Festival/winter8_12",
          "DialogueText": "Pekâlâ millet. Bu yılki buz balıkçılığı yarışmasına başlayalım.",
          "AudioPath": "assets/tr-TR/Lewis/255.ogg"
        },
        {
          "DialogueFrom": "Festival/winter8_13",
          "DialogueText": "Yarışmacılar, buz deliklerinden size sağlanan oltalar ile olabildiğince çok balık tutmalısınız.",
          "AudioPath": "assets/tr-TR/Lewis/256.ogg"
        },
        {
          "DialogueFrom": "Festival/winter8_14",
          "DialogueText": "Herkes hazır mı?",
          "AudioPath": "assets/tr-TR/Lewis/257.ogg"
        },
        {
          "DialogueFrom": "Festival/winter8_15",
          "DialogueText": "Başla!",
          "AudioPath": "assets/tr-TR/Lewis/258.ogg"
        },
        {
          "DialogueFrom": "Festival/winter8_16",
          "DialogueText": "Etkileyici, burada çok fazla balık var!",
          "AudioPath": "assets/tr-TR/Lewis/259.ogg"
        },
        {
          "DialogueFrom": "Festival/winter8_17",
          "DialogueText": "*öğürür*... Bu kokuya asla alışamayacağım...",
          "AudioPath": "assets/tr-TR/Lewis/260.ogg"
        },
        {
          "DialogueFrom": "Festival/winter8_18",
          "DialogueText": "Bu yılki buzda balık tutma yarışmasının kazananı...",
          "AudioPath": "assets/tr-TR/Lewis/261.ogg"
        },
        {
          "DialogueFrom": "Festival/winter8_20",
          "DialogueText": "Eh, bu yılki Buz Şöleni de bu kadardı. Geldiğiniz için teşekkürler millet!Artık şu zavallı balıkları salalım...",
          "AudioPath": "assets/tr-TR/Lewis/262.ogg"
        },
        {
          "DialogueFrom": "Festival/winter8_21",
          "DialogueText": "İşte ödülün Willy. Tadını çıkar.",
          "AudioPath": "assets/tr-TR/Lewis/263.ogg"
        },
        {
          "DialogueFrom": "Festival/winter8_23",
          "DialogueText": "Merhaba . Vakit geldi, buz balıkçılığı zamanı.Yarışmayı başlatmaya hazır olduğunda benimle konuş!",
          "AudioPath": "assets/tr-TR/Lewis/264.ogg"
        },
        {
          "DialogueFrom": "Festival/winter8_3",
          "DialogueText": "Başlayın!",
          "AudioPath": "assets/tr-TR/Lewis/265.ogg"
        },
        {
          "DialogueFrom": "Festival/winter8_4",
          "DialogueText": "Vay be, epey balık var!",
          "AudioPath": "assets/tr-TR/Lewis/266.ogg"
        },
        {
          "DialogueFrom": "Festival/winter8_5",
          "DialogueText": "*kusar*... Bu koku...",
          "AudioPath": "assets/tr-TR/Lewis/267.ogg"
        },
        {
          "DialogueFrom": "Festival/winter8_7",
          "DialogueText": "İşte ödülün!",
          "AudioPath": "assets/tr-TR/Lewis/268.ogg"
        },
        {
          "DialogueFrom": "Festival/winter8_8",
          "DialogueText": "Bu seneki Buz Şöleni burada sona eriyor. Geldiğiniz için teşekkürler, millet! Artık şu zavallı balıkları salalım...",
          "AudioPath": "assets/tr-TR/Lewis/269.ogg"
        },
        {
          "DialogueFrom": "Festival/winter8_9",
          "DialogueText": "İşte ödülün Willy, tadını çıkar.",
          "AudioPath": "assets/tr-TR/Lewis/270.ogg"
        },
        {
          "DialogueFrom": "NPCGiftTastes",
          "DialogueText": "Vay vay vay... Bu en sevdiğimden değil mi yav? Teşekkür ederim!",
          "AudioPath": "assets/tr-TR/Lewis/271.ogg"
        },
        {
          "DialogueFrom": "NPCGiftTastes_1",
          "DialogueText": "Teşekkürler, bu harika!",
          "AudioPath": "assets/tr-TR/Lewis/272.ogg"
        },
        {
          "DialogueFrom": "NPCGiftTastes_2",
          "DialogueText": "Eh, en azından düşünmüşsün...",
          "AudioPath": "assets/tr-TR/Lewis/273.ogg"
        },
        {
          "DialogueFrom": "NPCGiftTastes_3",
          "DialogueText": "İğrendim doğrusu. Ne kadar da korkunç bir hediye.",
          "AudioPath": "assets/tr-TR/Lewis/274.ogg"
        },
        {
          "DialogueFrom": "NPCGiftTastes_4",
          "DialogueText": "Çok hoşsun. Teşekkürler.",
          "AudioPath": "assets/tr-TR/Lewis/275.ogg"
        }
      ]
    }
  ]
}