{
  "Format": "2.0.0",
  "VoicePacks": [
    {
      "Format": "2.0.0",
      "VoicePackId": "DictionaryV2.Krobus.hu-HU",
      "VoicePackName": "DictionaryV2 (Krobus - hu-HU)",
      "Character": "Krobus",
      "Language": "hu-HU",
      "Entries": [
        {
          "DialogueFrom": "SpouseStardrop",
          "DialogueText": "Ezt egyfajta 'köszönésképpen' adnám neked, amiért megengedted, hogy itt élhessek veled. {Portrait:Happy}",
          "AudioPath": "assets/hu-HU/Krobus/1.ogg",
          "TranslationKey": "Characters/Dialogue/Krobus:SpouseStardrop",
          "PageIndex": 0,
          "DisplayPattern": "Ezt egyfajta 'köszönésképpen' adnám neked, amiért megengedted, hogy itt élhessek veled."
        },
        {
          "DialogueFrom": "4_*",
          "DialogueText": "...A bányákban találkoztál olyanokkal mint én? Sajnálom, ha ellenségesek voltak veled. Megtanultunk félni az emberektől... túl sok... kellemetlen találkozásunk volt.",
          "AudioPath": "assets/hu-HU/Krobus/2.ogg",
          "TranslationKey": "Characters/Dialogue/Krobus:4_*",
          "PageIndex": 0,
          "DisplayPattern": "...A bányákban találkoztál olyanokkal mint én? Sajnálom, ha ellenségesek voltak veled. Megtanultunk félni az emberektől... túl sok... kellemetlen találkozásunk volt."
        },
        {
          "DialogueFrom": "4_*",
          "DialogueText": "Nem... ölted meg egy barátomat sem, ugye?",
          "AudioPath": "assets/hu-HU/Krobus/3.ogg",
          "TranslationKey": "Characters/Dialogue/Krobus:4_*",
          "PageIndex": 1,
          "DisplayPattern": "Nem... ölted meg egy barátomat sem, ugye?"
        },
        {
          "DialogueFrom": "AcceptBirthdayGift_Positive",
          "DialogueText": "Ó, egy ajándék azon nap emlékére, amikor kikeltem! Köszönöm! {Portrait:Happy}",
          "AudioPath": "assets/hu-HU/Krobus/4.ogg",
          "TranslationKey": "Characters/Dialogue/Krobus:AcceptBirthdayGift_Positive",
          "PageIndex": 0,
          "DisplayPattern": "Ó, egy ajándék azon nap emlékére, amikor kikeltem! Köszönöm!"
        },
        {
          "DialogueFrom": "GreenRain",
          "DialogueText": "Ma a szokásosnál is erősebben folynak a vizek... mi történik odafent?",
          "AudioPath": "assets/hu-HU/Krobus/5.ogg",
          "TranslationKey": "Characters/Dialogue/Krobus:GreenRain",
          "PageIndex": 0,
          "DisplayPattern": "Ma a szokásosnál is erősebben folynak a vizek... mi történik odafent?"
        },
        {
          "DialogueFrom": "AcceptBirthdayGift_Negative",
          "DialogueText": "Ó... ezt nevezed 'születésnapi ajándéknak'? Nem értem az embereket... {Portrait:Sad}",
          "AudioPath": "assets/hu-HU/Krobus/6.ogg",
          "TranslationKey": "Characters/Dialogue/Krobus:AcceptBirthdayGift_Negative",
          "PageIndex": 0,
          "DisplayPattern": "Ó... ezt nevezed 'születésnapi ajándéknak'? Nem értem az embereket..."
        },
        {
          "DialogueFrom": "AcceptGift_(O)StardropTea",
          "DialogueText": "Az ott Csillaghulló tea? Köszönöm! Egyetlen csepp is elég, hogy a szobámnak egész nap jó illata legyen.",
          "AudioPath": "assets/hu-HU/Krobus/7.ogg",
          "TranslationKey": "Characters/Dialogue/Krobus:AcceptGift_(O)StardropTea",
          "PageIndex": 0,
          "DisplayPattern": "Az ott Csillaghulló tea? Köszönöm! Egyetlen csepp is elég, hogy a szobámnak egész nap jó illata legyen."
        },
        {
          "DialogueFrom": "AcceptGift_(O)Book_Void",
          "DialogueText": "Hé, nézd! Az összes barátom benne van! {Portrait:Happy}",
          "AudioPath": "assets/hu-HU/Krobus/8.ogg",
          "TranslationKey": "Characters/Dialogue/Krobus:AcceptGift_(O)Book_Void",
          "PageIndex": 0,
          "DisplayPattern": "Hé, nézd! Az összes barátom benne van!"
        },
        {
          "DialogueFrom": "AcceptGift_(O)Book_Void",
          "DialogueText": "Várjunk csak, az ott én volnék...? {Portrait:Custom:7}",
          "AudioPath": "assets/hu-HU/Krobus/9.ogg",
          "TranslationKey": "Characters/Dialogue/Krobus:AcceptGift_(O)Book_Void",
          "PageIndex": 1,
          "DisplayPattern": "Várjunk csak, az ott én volnék...?"
        },
        {
          "DialogueFrom": "AcceptGift_(O)879",
          "DialogueText": "Egy kedves parfümös ajándék? Óh, {Farmer_Name}... Elpirultam, de gondolom nem veszed észre... {Portrait:Love}",
          "AudioPath": "assets/hu-HU/Krobus/10.ogg",
          "TranslationKey": "Characters/Dialogue/Krobus:AcceptGift_(O)879",
          "PageIndex": 0,
          "DisplayPattern": "Egy kedves parfümös ajándék? Óh, ... Elpirultam, de gondolom nem veszed észre..."
        },
        {
          "DialogueFrom": "AcceptGift_(O)308",
          "DialogueText": "Az illata alapján ízletes! A felét megeszem, a másik felével pedig hidratálni fogom a testemet... {Portrait:Happy}",
          "AudioPath": "assets/hu-HU/Krobus/11.ogg",
          "TranslationKey": "Characters/Dialogue/Krobus:AcceptGift_(O)308",
          "PageIndex": 0,
          "DisplayPattern": "Az illata alapján ízletes! A felét megeszem, a másik felével pedig hidratálni fogom a testemet..."
        },
        {
          "DialogueFrom": "8_*",
          "DialogueText": "Nemrég ért véget egy ezer éves háború a népem és a törpék között. A neheztelés még mindig erős mind a két oldalon.",
          "AudioPath": "assets/hu-HU/Krobus/12.ogg",
          "TranslationKey": "Characters/Dialogue/Krobus:8_*",
          "PageIndex": 0,
          "DisplayPattern": "Nemrég ért véget egy ezer éves háború a népem és a törpék között. A neheztelés még mindig erős mind a két oldalon."
        },
        {
          "DialogueFrom": "15_*",
          "DialogueText": "Kérlek tartsd titokban a búvóhelyemet. Ha a törpék tudnának rólam, biztosan bérgyilkost küldenének.",
          "AudioPath": "assets/hu-HU/Krobus/13.ogg",
          "TranslationKey": "Characters/Dialogue/Krobus:15_*",
          "PageIndex": 0,
          "DisplayPattern": "Kérlek tartsd titokban a búvóhelyemet. Ha a törpék tudnának rólam, biztosan bérgyilkost küldenének."
        },
        {
          "DialogueFrom": "18_*",
          "DialogueText": "Próbálok nem túl sok zajt okozni idelent. Képzeld el mit gondolnának a városlakók, ha fura zajokat hallanának a lefolyóból...",
          "AudioPath": "assets/hu-HU/Krobus/14.ogg",
          "TranslationKey": "Characters/Dialogue/Krobus:18_*",
          "PageIndex": 0,
          "DisplayPattern": "Próbálok nem túl sok zajt okozni idelent. Képzeld el mit gondolnának a városlakók, ha fura zajokat hallanának a lefolyóból..."
        },
        {
          "DialogueFrom": "Fri",
          "DialogueText": "...",
          "AudioPath": "assets/hu-HU/Krobus/15.ogg",
          "TranslationKey": "Characters/Dialogue/Krobus:Fri",
          "PageIndex": 0,
          "DisplayPattern": "..."
        },
        {
          "DialogueFrom": "eventSeen_691039",
          "DialogueText": "...Kissé megsérültem, de amúgy jól vagyok.",
          "AudioPath": "assets/hu-HU/Krobus/16.ogg",
          "TranslationKey": "Characters/Dialogue/Krobus:eventSeen_691039",
          "PageIndex": 0,
          "DisplayPattern": "...Kissé megsérültem, de amúgy jól vagyok."
        },
        {
          "DialogueFrom": "reject_868",
          "DialogueText": "Ó, az egy sarki töredék! Az egy nagyon ritka mágikus tárgy.",
          "AudioPath": "assets/hu-HU/Krobus/17.ogg",
          "TranslationKey": "Characters/Dialogue/Krobus:reject_868",
          "PageIndex": 0,
          "DisplayPattern": "Ó, az egy sarki töredék! Az egy nagyon ritka mágikus tárgy."
        },
        {
          "DialogueFrom": "reject_868",
          "DialogueText": "Én a helyedben elvinném a Varázslónak.",
          "AudioPath": "assets/hu-HU/Krobus/18.ogg",
          "TranslationKey": "Characters/Dialogue/Krobus:reject_868",
          "PageIndex": 1,
          "DisplayPattern": "Én a helyedben elvinném a Varázslónak."
        },
        {
          "DialogueFrom": "Wed",
          "DialogueText": "Olyan dolgokat árulok, amiket itt találtam. Kínálhatlak valamivel?",
          "AudioPath": "assets/hu-HU/Krobus/19.ogg",
          "TranslationKey": "Characters/Dialogue/Krobus:Wed",
          "PageIndex": 0,
          "DisplayPattern": "Olyan dolgokat árulok, amiket itt találtam. Kínálhatlak valamivel?"
        },
        {
          "DialogueFrom": "Wed6",
          "DialogueText": "Ha a füledet ehhez a csőhöz helyezed, akkor bármelyik ház hangját hallhatod.",
          "AudioPath": "assets/hu-HU/Krobus/20.ogg",
          "TranslationKey": "Characters/Dialogue/Krobus:Wed6",
          "PageIndex": 0,
          "DisplayPattern": "Ha a füledet ehhez a csőhöz helyezed, akkor bármelyik ház hangját hallhatod."
        },
        {
          "DialogueFrom": "Wed6",
          "DialogueText": "Habár én nem hallgatóznék! {Portrait:Unique}",
          "AudioPath": "assets/hu-HU/Krobus/21.ogg",
          "TranslationKey": "Characters/Dialogue/Krobus:Wed6",
          "PageIndex": 1,
          "DisplayPattern": "Habár én nem hallgatóznék!"
        },
        {
          "DialogueFrom": "Thu",
          "DialogueText": "Kérlek ne szólj rólam senkinek.",
          "AudioPath": "assets/hu-HU/Krobus/22.ogg",
          "TranslationKey": "Characters/Dialogue/Krobus:Thu",
          "PageIndex": 0,
          "DisplayPattern": "Kérlek ne szólj rólam senkinek."
        },
        {
          "DialogueFrom": "Thu",
          "DialogueText": "Az emberek általában elpusztítják amit nem értenek meg.",
          "AudioPath": "assets/hu-HU/Krobus/23.ogg",
          "TranslationKey": "Characters/Dialogue/Krobus:Thu",
          "PageIndex": 1,
          "DisplayPattern": "Az emberek általában elpusztítják amit nem értenek meg."
        },
        {
          "DialogueFrom": "Thu6",
          "DialogueText": "Kérlek senkinek se mesélj rólam.",
          "AudioPath": "assets/hu-HU/Krobus/24.ogg",
          "TranslationKey": "Characters/Dialogue/Krobus:Thu6",
          "PageIndex": 0,
          "DisplayPattern": "Kérlek senkinek se mesélj rólam."
        },
        {
          "DialogueFrom": "Thu6",
          "DialogueText": "A legtöbb ember fél tőlünk árnyékemberektől... talán jó okkal. {Portrait:Sad}",
          "AudioPath": "assets/hu-HU/Krobus/25.ogg",
          "TranslationKey": "Characters/Dialogue/Krobus:Thu6",
          "PageIndex": 1,
          "DisplayPattern": "A legtöbb ember fél tőlünk árnyékemberektől... talán jó okkal."
        },
        {
          "DialogueFrom": "Thu6",
          "DialogueText": "De ez nem számít, ha a városiak tudnának rólam, akkor nem lennék itt biztonságban.",
          "AudioPath": "assets/hu-HU/Krobus/26.ogg",
          "TranslationKey": "Characters/Dialogue/Krobus:Thu6",
          "PageIndex": 2,
          "DisplayPattern": "De ez nem számít, ha a városiak tudnának rólam, akkor nem lennék itt biztonságban."
        },
        {
          "DialogueFrom": "Tue",
          "DialogueText": "A legtöbb napon túl érzékeny vagyok a napfényre ahhoz, hogy világosban kimenjek.",
          "AudioPath": "assets/hu-HU/Krobus/27.ogg",
          "TranslationKey": "Characters/Dialogue/Krobus:Tue",
          "PageIndex": 0,
          "DisplayPattern": "A legtöbb napon túl érzékeny vagyok a napfényre ahhoz, hogy világosban kimenjek."
        },
        {
          "DialogueFrom": "Tue",
          "DialogueText": "Itt tökéletesek a körülmények.",
          "AudioPath": "assets/hu-HU/Krobus/28.ogg",
          "TranslationKey": "Characters/Dialogue/Krobus:Tue",
          "PageIndex": 1,
          "DisplayPattern": "Itt tökéletesek a körülmények."
        },
        {
          "DialogueFrom": "Tue",
          "DialogueText": "Kínálhatlak valamivel?",
          "AudioPath": "assets/hu-HU/Krobus/29.ogg",
          "TranslationKey": "Characters/Dialogue/Krobus:Tue",
          "PageIndex": 2,
          "DisplayPattern": "Kínálhatlak valamivel?"
        },
        {
          "DialogueFrom": "Mon",
          "DialogueText": "Kérlek, ne ijedj meg. Más vagyok mint a többiek.",
          "AudioPath": "assets/hu-HU/Krobus/30.ogg",
          "TranslationKey": "Characters/Dialogue/Krobus:Mon",
          "PageIndex": 0,
          "DisplayPattern": "Kérlek, ne ijedj meg. Más vagyok mint a többiek."
        },
        {
          "DialogueFrom": "Mon",
          "DialogueText": "Sok időt töltöttem az emberek megfigyelésével. Tudom, hogy szerettek vásárolni. Szeretnéd látni a portékámat?",
          "AudioPath": "assets/hu-HU/Krobus/31.ogg",
          "TranslationKey": "Characters/Dialogue/Krobus:Mon",
          "PageIndex": 1,
          "DisplayPattern": "Sok időt töltöttem az emberek megfigyelésével. Tudom, hogy szerettek vásárolni. Szeretnéd látni a portékámat?"
        },
        {
          "DialogueFrom": "Mon2",
          "DialogueText": "Újra itt? Ez a viselkedés beleillik az emberekről alkotott elméletembe.",
          "AudioPath": "assets/hu-HU/Krobus/32.ogg",
          "TranslationKey": "Characters/Dialogue/Krobus:Mon2",
          "PageIndex": 0,
          "DisplayPattern": "Újra itt? Ez a viselkedés beleillik az emberekről alkotott elméletembe."
        },
        {
          "DialogueFrom": "Mon6",
          "DialogueText": "A 'Krobus' népem nyelvén azt jelenti: 'hídjáró'.",
          "AudioPath": "assets/hu-HU/Krobus/33.ogg",
          "TranslationKey": "Characters/Dialogue/Krobus:Mon6",
          "PageIndex": 0,
          "DisplayPattern": "A 'Krobus' népem nyelvén azt jelenti: 'hídjáró'."
        },
        {
          "DialogueFrom": "Sat",
          "DialogueText": "Péntekenként Yoba iránt mutatott tiszteletem jeléül csendben maradok.",
          "AudioPath": "assets/hu-HU/Krobus/34.ogg",
          "TranslationKey": "Characters/Dialogue/Krobus:Sat",
          "PageIndex": 0,
          "DisplayPattern": "Péntekenként Yoba iránt mutatott tiszteletem jeléül csendben maradok."
        },
        {
          "DialogueFrom": "Sat4",
          "DialogueText": "Szeretnék többet látni a külvilágból, de nem lenne biztonságos számomra. {Portrait:Sad}",
          "AudioPath": "assets/hu-HU/Krobus/35.ogg",
          "TranslationKey": "Characters/Dialogue/Krobus:Sat4",
          "PageIndex": 0,
          "DisplayPattern": "Szeretnék többet látni a külvilágból, de nem lenne biztonságos számomra."
        },
        {
          "DialogueFrom": "Sat8",
          "DialogueText": "Soha nem fogom megtudni, hogy milyen embernek lenni... de a veled való beszélgetésekből úgy érzem, hogy kissé kezdem megérteni.",
          "AudioPath": "assets/hu-HU/Krobus/36.ogg",
          "TranslationKey": "Characters/Dialogue/Krobus:Sat8",
          "PageIndex": 0,
          "DisplayPattern": "Soha nem fogom megtudni, hogy milyen embernek lenni... de a veled való beszélgetésekből úgy érzem, hogy kissé kezdem megérteni."
        },
        {
          "DialogueFrom": "Sun",
          "DialogueText": "...Bocsánat, még mindig tartok kicsit az emberektől. Ennek ellenére a boltom továbbra is nyitva áll számodra.",
          "AudioPath": "assets/hu-HU/Krobus/37.ogg",
          "TranslationKey": "Characters/Dialogue/Krobus:Sun",
          "PageIndex": 0,
          "DisplayPattern": "...Bocsánat, még mindig tartok kicsit az emberektől. Ennek ellenére a boltom továbbra is nyitva áll számodra."
        },
        {
          "DialogueFrom": "Sun4",
          "DialogueText": "Te nem olyan vagy, mint a többi ember, igaz-e?",
          "AudioPath": "assets/hu-HU/Krobus/38.ogg",
          "TranslationKey": "Characters/Dialogue/Krobus:Sun4",
          "PageIndex": 0,
          "DisplayPattern": "Te nem olyan vagy, mint a többi ember, igaz-e?"
        },
        {
          "DialogueFrom": "Sun8",
          "DialogueText": "Felnyitottad a szemem az emberek világára. Hálás vagyok érte.",
          "AudioPath": "assets/hu-HU/Krobus/39.ogg",
          "TranslationKey": "Characters/Dialogue/Krobus:Sun8",
          "PageIndex": 0,
          "DisplayPattern": "Felnyitottad a szemem az emberek világára. Hálás vagyok érte."
        },
        {
          "DialogueFrom": "divorced",
          "DialogueText": "...",
          "AudioPath": "assets/hu-HU/Krobus/40.ogg",
          "TranslationKey": "Characters/Dialogue/Krobus:divorced",
          "PageIndex": 0,
          "DisplayPattern": "..."
        },
        {
          "DialogueFrom": "EngagementDialogue/Krobus0",
          "DialogueText": "{Farmer_Name}... Attól tartok, hogy ezt titokban kell tartanunk... Sem a te néped, sem az enyém nem fogadná el azt, hogy együtt élünk.",
          "AudioPath": "assets/hu-HU/Krobus/41.ogg",
          "TranslationKey": "Data/EngagementDialogue:Krobus0",
          "PageIndex": 0,
          "DisplayPattern": "... Attól tartok, hogy ezt titokban kell tartanunk... Sem a te néped, sem az enyém nem fogadná el azt, hogy együtt élünk."
        },
        {
          "DialogueFrom": "EngagementDialogue/Krobus1",
          "DialogueText": "Tudod nagyon fura lesz velem élni, ugye? Nem fogom tudni elhagyni a házat...",
          "AudioPath": "assets/hu-HU/Krobus/42.ogg",
          "TranslationKey": "Data/EngagementDialogue:Krobus1",
          "PageIndex": 0,
          "DisplayPattern": "Tudod nagyon fura lesz velem élni, ugye? Nem fogom tudni elhagyni a házat..."
        },
        {
          "DialogueFrom": "Marriage/Krobus/Bad_0",
          "DialogueText": "...Még mindig kedvelsz engem? {Portrait:Sad}",
          "AudioPath": "assets/hu-HU/Krobus/43.ogg",
          "TranslationKey": "Characters/Dialogue/MarriageDialogueKrobus:Bad_0",
          "PageIndex": 0,
          "DisplayPattern": "...Még mindig kedvelsz engem?"
        },
        {
          "DialogueFrom": "Marriage/Krobus/Bad_1",
          "DialogueText": "*sóhaj*... Talán a saját fajtámmal kellett volna maradnom. {Portrait:Sad}",
          "AudioPath": "assets/hu-HU/Krobus/44.ogg",
          "TranslationKey": "Characters/Dialogue/MarriageDialogueKrobus:Bad_1",
          "PageIndex": 0,
          "DisplayPattern": "*sóhaj*... Talán a saját fajtámmal kellett volna maradnom."
        },
        {
          "DialogueFrom": "Marriage/Krobus/Bad_2",
          "DialogueText": "Még mindig boldog vagy, hogy velem élsz? {Portrait:Sad}",
          "AudioPath": "assets/hu-HU/Krobus/45.ogg",
          "TranslationKey": "Characters/Dialogue/MarriageDialogueKrobus:Bad_2",
          "PageIndex": 0,
          "DisplayPattern": "Még mindig boldog vagy, hogy velem élsz?"
        },
        {
          "DialogueFrom": "Marriage/Krobus/Bad_3",
          "DialogueText": "Valami rosszat csináltam? Mostanság olyan furán viselkedsz. {Portrait:Sad}",
          "AudioPath": "assets/hu-HU/Krobus/46.ogg",
          "TranslationKey": "Characters/Dialogue/MarriageDialogue:Bad_3",
          "PageIndex": 0,
          "DisplayPattern": "Valami rosszat csináltam? Mostanság olyan furán viselkedsz."
        },
        {
          "DialogueFrom": "Marriage/Krobus/Bad_4",
          "DialogueText": "Szerintem egy másik emberrel boldogabban élnél... {Portrait:Sad}",
          "AudioPath": "assets/hu-HU/Krobus/47.ogg",
          "TranslationKey": "Characters/Dialogue/MarriageDialogueKrobus:Bad_4",
          "PageIndex": 0,
          "DisplayPattern": "Szerintem egy másik emberrel boldogabban élnél..."
        },
        {
          "DialogueFrom": "Marriage/Krobus/Bad_5",
          "DialogueText": "Változást észleltem a viselkedésedben... ez mégis mit jelent? *morog* {Portrait:Sad}",
          "AudioPath": "assets/hu-HU/Krobus/48.ogg",
          "TranslationKey": "Characters/Dialogue/MarriageDialogueKrobus:Bad_5",
          "PageIndex": 0,
          "DisplayPattern": "Változást észleltem a viselkedésedben... ez mégis mit jelent? *morog*"
        },
        {
          "DialogueFrom": "Marriage/Krobus/Bad_6",
          "DialogueText": "Neked csak egy rövid életed van... biztos, hogy mindezt egy olyan förtelmes lénnyel akarod eltölteni, mint én? {Portrait:Sad}",
          "AudioPath": "assets/hu-HU/Krobus/49.ogg",
          "TranslationKey": "Characters/Dialogue/MarriageDialogueKrobus:Bad_6",
          "PageIndex": 0,
          "DisplayPattern": "Neked csak egy rövid életed van... biztos, hogy mindezt egy olyan förtelmes lénnyel akarod eltölteni, mint én?"
        },
        {
          "DialogueFrom": "Marriage/Krobus/Bad_7",
          "DialogueText": "Talán az efféle kapcsolat amúgy se lenne működőképes... {Portrait:Sad}",
          "AudioPath": "assets/hu-HU/Krobus/50.ogg",
          "TranslationKey": "Characters/Dialogue/MarriageDialogueKrobus:Bad_7",
          "PageIndex": 0,
          "DisplayPattern": "Talán az efféle kapcsolat amúgy se lenne működőképes..."
        },
        {
          "DialogueFrom": "Marriage/Krobus/Bad_8",
          "DialogueText": "Mostanság boldogtalannak tűnsz... {Portrait:Sad}",
          "AudioPath": "assets/hu-HU/Krobus/51.ogg",
          "TranslationKey": "Characters/Dialogue/MarriageDialogueKrobus:Bad_8",
          "PageIndex": 0,
          "DisplayPattern": "Mostanság boldogtalannak tűnsz..."
        },
        {
          "DialogueFrom": "Marriage/Krobus/Bad_9",
          "DialogueText": "Hiányzik a csatorna. {Portrait:Sad}",
          "AudioPath": "assets/hu-HU/Krobus/52.ogg",
          "TranslationKey": "Characters/Dialogue/MarriageDialogueKrobus:Bad_9",
          "PageIndex": 0,
          "DisplayPattern": "Hiányzik a csatorna."
        },
        {
          "DialogueFrom": "Marriage/Krobus/fall_1",
          "DialogueText": "Ez az idő olyan jól esik a nyári hőség után.",
          "AudioPath": "assets/hu-HU/Krobus/53.ogg",
          "TranslationKey": "Characters/Dialogue/MarriageDialogue:fall_1",
          "PageIndex": 0,
          "DisplayPattern": "Ez az idő olyan jól esik a nyári hőség után."
        },
        {
          "DialogueFrom": "Marriage/Krobus/fall_12",
          "DialogueText": "...",
          "AudioPath": "assets/hu-HU/Krobus/54.ogg",
          "TranslationKey": "Characters/Dialogue/MarriageDialogueKrobus:fall_12",
          "PageIndex": 0,
          "DisplayPattern": "..."
        },
        {
          "DialogueFrom": "Marriage/Krobus/fall_15",
          "DialogueText": "Kitaláltad már, hogy mit fogsz holnap a kirakatodba helyezni?",
          "AudioPath": "assets/hu-HU/Krobus/55.ogg",
          "TranslationKey": "Characters/Dialogue/MarriageDialogueKrobus:fall_15",
          "PageIndex": 0,
          "DisplayPattern": "Kitaláltad már, hogy mit fogsz holnap a kirakatodba helyezni?"
        },
        {
          "DialogueFrom": "Marriage/Krobus/fall_19",
          "DialogueText": "...",
          "AudioPath": "assets/hu-HU/Krobus/56.ogg",
          "TranslationKey": "Characters/Dialogue/MarriageDialogueKrobus:fall_19",
          "PageIndex": 0,
          "DisplayPattern": "..."
        },
        {
          "DialogueFrom": "Marriage/Krobus/fall_24",
          "DialogueText": "Ha holnap felbukkannék a Lelkek Éjszakájának fesztiválján, biztos, hogy ketrecbe zárnának... {Portrait:Sad}",
          "AudioPath": "assets/hu-HU/Krobus/57.ogg",
          "TranslationKey": "Characters/Dialogue/MarriageDialogueKrobus:fall_24",
          "PageIndex": 0,
          "DisplayPattern": "Ha holnap felbukkannék a Lelkek Éjszakájának fesztiválján, biztos, hogy ketrecbe zárnának..."
        },
        {
          "DialogueFrom": "Marriage/Krobus/fall_26",
          "DialogueText": "...",
          "AudioPath": "assets/hu-HU/Krobus/58.ogg",
          "TranslationKey": "Characters/Dialogue/MarriageDialogueKrobus:fall_26",
          "PageIndex": 0,
          "DisplayPattern": "..."
        },
        {
          "DialogueFrom": "Marriage/Krobus/fall_5",
          "DialogueText": "...",
          "AudioPath": "assets/hu-HU/Krobus/59.ogg",
          "TranslationKey": "Characters/Dialogue/MarriageDialogueKrobus:fall_5",
          "PageIndex": 0,
          "DisplayPattern": "..."
        },
        {
          "DialogueFrom": "Marriage/Krobus/fall_8",
          "DialogueText": "Úgy érzem ma semmihez sincs kedvem.",
          "AudioPath": "assets/hu-HU/Krobus/60.ogg",
          "TranslationKey": "Characters/Dialogue/MarriageDialogueKrobus:fall_8",
          "PageIndex": 0,
          "DisplayPattern": "Úgy érzem ma semmihez sincs kedvem."
        },
        {
          "DialogueFrom": "Marriage/Krobus/fall_Krobus",
          "DialogueText": "Mostanság kissé fázósnak érzem magam, és olyan dohos illat van. Jól emlékszem, hogy ezt az időszakot 'ősznek' nevezitek, ugye?",
          "AudioPath": "assets/hu-HU/Krobus/61.ogg",
          "TranslationKey": "Characters/Dialogue/MarriageDialogueKrobus:fall_Krobus",
          "PageIndex": 0,
          "DisplayPattern": "Mostanság kissé fázósnak érzem magam, és olyan dohos illat van. Jól emlékszem, hogy ezt az időszakot 'ősznek' nevezitek, ugye?"
        },
        {
          "DialogueFrom": "Marriage/Krobus/Good_0",
          "DialogueText": "Jól haladunk, és így tele vagyok reménnyel. {Portrait:Happy}",
          "AudioPath": "assets/hu-HU/Krobus/62.ogg",
          "TranslationKey": "Characters/Dialogue/MarriageDialogueKrobus:Good_0",
          "PageIndex": 0,
          "DisplayPattern": "Jól haladunk, és így tele vagyok reménnyel."
        },
        {
          "DialogueFrom": "Marriage/Krobus/Good_1",
          "DialogueText": "Furcsa érzés kavarog a testemben... ez lenne a... 'plátói szerelem'? {Portrait:Love}",
          "AudioPath": "assets/hu-HU/Krobus/63.ogg",
          "TranslationKey": "Characters/Dialogue/MarriageDialogueKrobus:Good_1",
          "PageIndex": 0,
          "DisplayPattern": "Furcsa érzés kavarog a testemben... ez lenne a... 'plátói szerelem'?"
        },
        {
          "DialogueFrom": "Marriage/Krobus/Good_1",
          "DialogueText": "... Óh, várjunk... épp vedlek. {Portrait:Sad}",
          "AudioPath": "assets/hu-HU/Krobus/64.ogg",
          "TranslationKey": "Characters/Dialogue/MarriageDialogueKrobus:Good_1",
          "PageIndex": 1,
          "DisplayPattern": "... Óh, várjunk... épp vedlek."
        },
        {
          "DialogueFrom": "Marriage/Krobus/Good_2",
          "DialogueText": "Megtanultam leküzdeni az előítéleteimet az emberekkel szemben... de a Törpéktől továbbra is undorodom. {Portrait:Angry}",
          "AudioPath": "assets/hu-HU/Krobus/65.ogg",
          "TranslationKey": "Characters/Dialogue/MarriageDialogueKrobus:Good_2",
          "PageIndex": 0,
          "DisplayPattern": "Megtanultam leküzdeni az előítéleteimet az emberekkel szemben... de a Törpéktől továbbra is undorodom."
        },
        {
          "DialogueFrom": "Marriage/Krobus/Good_3",
          "DialogueText": "Este harapdálni kezdtél engem, és valami 'fekete nyaló vagy káról' mormogtál... mégis mire céloztál ezzel? {Portrait:Unique}",
          "AudioPath": "assets/hu-HU/Krobus/66.ogg",
          "TranslationKey": "Characters/Dialogue/MarriageDialogueKrobus:Good_3",
          "PageIndex": 0,
          "DisplayPattern": "Este harapdálni kezdtél engem, és valami 'fekete nyaló vagy káról' mormogtál... mégis mire céloztál ezzel?"
        },
        {
          "DialogueFrom": "Marriage/Krobus/Good_4",
          "DialogueText": "Mostantól ez a hely az otthonom... Itt boldog vagyok. {Portrait:Love}",
          "AudioPath": "assets/hu-HU/Krobus/67.ogg",
          "TranslationKey": "Characters/Dialogue/MarriageDialogue:Good_4",
          "PageIndex": 0,
          "DisplayPattern": "Mostantól ez a hely az otthonom... Itt boldog vagyok."
        },
        {
          "DialogueFrom": "Marriage/Krobus/Good_5",
          "DialogueText": "Épp csak csodáltam ezt a szép házat... milyen csodálatos ez a hely. {Portrait:Love}",
          "AudioPath": "assets/hu-HU/Krobus/68.ogg",
          "TranslationKey": "Characters/Dialogue/MarriageDialogueKrobus:Good_5",
          "PageIndex": 0,
          "DisplayPattern": "Épp csak csodáltam ezt a szép házat... milyen csodálatos ez a hely."
        },
        {
          "DialogueFrom": "Marriage/Krobus/Good_6",
          "DialogueText": "Légy óvatos odakint! Néha aggódom, nehogy lezuhanj egy bányaaknába.",
          "AudioPath": "assets/hu-HU/Krobus/69.ogg",
          "TranslationKey": "Characters/Dialogue/MarriageDialogue:Good_6",
          "PageIndex": 0,
          "DisplayPattern": "Légy óvatos odakint! Néha aggódom, nehogy lezuhanj egy bányaaknába."
        },
        {
          "DialogueFrom": "Marriage/Krobus/Good_7",
          "DialogueText": "{Farmer_Name}? Csak értékelni szeretném azt a rengeteg munkát, amit a háztartásért teszel. {Portrait:Happy}",
          "AudioPath": "assets/hu-HU/Krobus/70.ogg",
          "TranslationKey": "Characters/Dialogue/MarriageDialogue:Good_7",
          "PageIndex": 0,
          "DisplayPattern": "? Csak értékelni szeretném azt a rengeteg munkát, amit a háztartásért teszel."
        },
        {
          "DialogueFrom": "Marriage/Krobus/Good_8",
          "DialogueText": "Ne aggódj miattam... Tudom, hogy rengeteg felelősséged van a házon kívül is. Remekül megvagyok egyedül is! {Portrait:Love}",
          "AudioPath": "assets/hu-HU/Krobus/71.ogg",
          "TranslationKey": "Characters/Dialogue/MarriageDialogue:Good_8",
          "PageIndex": 0,
          "DisplayPattern": "Ne aggódj miattam... Tudom, hogy rengeteg felelősséged van a házon kívül is. Remekül megvagyok egyedül is!"
        },
        {
          "DialogueFrom": "Marriage/Krobus/Good_9",
          "DialogueText": "Ó, nem unatkozom... Csak élvezem mindazt, amink van.",
          "AudioPath": "assets/hu-HU/Krobus/72.ogg",
          "TranslationKey": "Characters/Dialogue/MarriageDialogue:Good_9",
          "PageIndex": 0,
          "DisplayPattern": "Ó, nem unatkozom... Csak élvezem mindazt, amink van."
        },
        {
          "DialogueFrom": "Marriage/Krobus/Good_9",
          "DialogueText": "Ez egy egyszerű élet, de szeretem. {Portrait:Happy}",
          "AudioPath": "assets/hu-HU/Krobus/73.ogg",
          "TranslationKey": "Characters/Dialogue/MarriageDialogue:Good_9",
          "PageIndex": 1,
          "DisplayPattern": "Ez egy egyszerű élet, de szeretem."
        },
        {
          "DialogueFrom": "Marriage/Krobus/Indoor_Day_0",
          "DialogueText": "Ha jöhetnék segíteni neked, megtenném... de jobb, ha megpróbálom rendben tartani a házat.",
          "AudioPath": "assets/hu-HU/Krobus/74.ogg",
          "TranslationKey": "Characters/Dialogue/MarriageDialogueKrobus:Indoor_Day_0",
          "PageIndex": 0,
          "DisplayPattern": "Ha jöhetnék segíteni neked, megtenném... de jobb, ha megpróbálom rendben tartani a házat."
        },
        {
          "DialogueFrom": "Marriage/Krobus/Indoor_Day_1",
          "DialogueText": "Próbáltam emberi ételt készíteni... [203 204 651 225]",
          "AudioPath": "assets/hu-HU/Krobus/75.ogg",
          "TranslationKey": "Characters/Dialogue/MarriageDialogueKrobus:Indoor_Day_1",
          "PageIndex": 0,
          "DisplayPattern": "Próbáltam emberi ételt készíteni..."
        },
        {
          "DialogueFrom": "Marriage/Krobus/Indoor_Day_1",
          "DialogueText": "Ne aggódj, később is megeheted...",
          "AudioPath": "assets/hu-HU/Krobus/76.ogg",
          "TranslationKey": "Characters/Dialogue/MarriageDialogueKrobus:Indoor_Day_1",
          "PageIndex": 1,
          "DisplayPattern": "Ne aggódj, később is megeheted..."
        },
        {
          "DialogueFrom": "Marriage/Krobus/Indoor_Day_2",
          "DialogueText": "Boldog vagyok idebent a házban. Szeretem az időmet egy jó helyen tölteni... Nem kell \"kimozdulnom\", mint a legtöbb embernek.",
          "AudioPath": "assets/hu-HU/Krobus/77.ogg",
          "TranslationKey": "Characters/Dialogue/MarriageDialogueKrobus:Indoor_Day_2",
          "PageIndex": 0,
          "DisplayPattern": "Boldog vagyok idebent a házban. Szeretem az időmet egy jó helyen tölteni... Nem kell \"kimozdulnom\", mint a legtöbb embernek."
        },
        {
          "DialogueFrom": "Marriage/Krobus/Indoor_Day_2",
          "DialogueText": "De megértelek, ha neked igen! Kérlek ne érezd úgy magad, hogy itt kell maradnod velem. {Portrait:Unique}",
          "AudioPath": "assets/hu-HU/Krobus/78.ogg",
          "TranslationKey": "Characters/Dialogue/MarriageDialogueKrobus:Indoor_Day_2",
          "PageIndex": 1,
          "DisplayPattern": "De megértelek, ha neked igen! Kérlek ne érezd úgy magad, hogy itt kell maradnod velem."
        },
        {
          "DialogueFrom": "Marriage/Krobus/Indoor_Day_3",
          "DialogueText": "Azon tűnődöm, hogy egész nap begubózok majd a sarokba...",
          "AudioPath": "assets/hu-HU/Krobus/79.ogg",
          "TranslationKey": "Characters/Dialogue/MarriageDialogueKrobus:Indoor_Day_3",
          "PageIndex": 0,
          "DisplayPattern": "Azon tűnődöm, hogy egész nap begubózok majd a sarokba..."
        },
        {
          "DialogueFrom": "Marriage/Krobus/Indoor_Day_3",
          "DialogueText": "Micsoda? Azt mondod, hogy te ilyet nem csinálsz? {Portrait:Unique}",
          "AudioPath": "assets/hu-HU/Krobus/80.ogg",
          "TranslationKey": "Characters/Dialogue/MarriageDialogueKrobus:Indoor_Day_3",
          "PageIndex": 1,
          "DisplayPattern": "Micsoda? Azt mondod, hogy te ilyet nem csinálsz?"
        },
        {
          "DialogueFrom": "Marriage/Krobus/Indoor_Day_4",
          "DialogueText": "Péntekenként szeretek csendben maradni Yoba tiszteletére. Remélem ez téged nem zavar.",
          "AudioPath": "assets/hu-HU/Krobus/81.ogg",
          "TranslationKey": "Characters/Dialogue/MarriageDialogueKrobus:Indoor_Day_4",
          "PageIndex": 0,
          "DisplayPattern": "Péntekenként szeretek csendben maradni Yoba tiszteletére. Remélem ez téged nem zavar."
        },
        {
          "DialogueFrom": "Marriage/Krobus/Indoor_Day_Krobus",
          "DialogueText": "Bárcsak segíthetnék neked a farmon, de nem mehetek ki a napra...",
          "AudioPath": "assets/hu-HU/Krobus/82.ogg",
          "TranslationKey": "Characters/Dialogue/MarriageDialogueKrobus:Indoor_Day_Krobus",
          "PageIndex": 0,
          "DisplayPattern": "Bárcsak segíthetnék neked a on, de nem mehetek ki a napra..."
        },
        {
          "DialogueFrom": "Marriage/Krobus/Indoor_Night_0",
          "DialogueText": "Minden rovart eltakarítottam a házból... Elnézést, de neked egyet se hagytam! *cuppanás* {Portrait:Custom:7}",
          "AudioPath": "assets/hu-HU/Krobus/83.ogg",
          "TranslationKey": "Characters/Dialogue/MarriageDialogueKrobus:Indoor_Night_0",
          "PageIndex": 0,
          "DisplayPattern": "Minden rovart eltakarítottam a házból... Elnézést, de neked egyet se hagytam! *cuppanás*"
        },
        {
          "DialogueFrom": "Marriage/Krobus/Indoor_Night_1",
          "DialogueText": "Keménynek tűnsz... néha én is azt kívánom, hogy bár lennének csontjaim... {Portrait:Sad}",
          "AudioPath": "assets/hu-HU/Krobus/84.ogg",
          "TranslationKey": "Characters/Dialogue/MarriageDialogueKrobus:Indoor_Night_1",
          "PageIndex": 0,
          "DisplayPattern": "Keménynek tűnsz... néha én is azt kívánom, hogy bár lennének csontjaim..."
        },
        {
          "DialogueFrom": "Marriage/Krobus/Indoor_Night_2",
          "DialogueText": "Néha azon tűnődöm, hogy élhetnének-e együtt az emberek és az árnyékemberek... Bájos ötlet, de realisztikus? {Portrait:Sad}",
          "AudioPath": "assets/hu-HU/Krobus/85.ogg",
          "TranslationKey": "Characters/Dialogue/MarriageDialogueKrobus:Indoor_Night_2",
          "PageIndex": 0,
          "DisplayPattern": "Néha azon tűnődöm, hogy élhetnének-e együtt az emberek és az árnyékemberek... Bájos ötlet, de realisztikus?"
        },
        {
          "DialogueFrom": "Marriage/Krobus/Indoor_Night_2",
          "DialogueText": "Remélem is...",
          "AudioPath": "assets/hu-HU/Krobus/86.ogg",
          "TranslationKey": "Characters/Dialogue/MarriageDialogueKrobus:Indoor_Night_2",
          "PageIndex": 1,
          "DisplayPattern": "Remélem is..."
        },
        {
          "DialogueFrom": "Marriage/Krobus/Indoor_Night_3",
          "DialogueText": "Néha megállok és eltöprengek azon, hogy mit tanultam az emberekről tőled...",
          "AudioPath": "assets/hu-HU/Krobus/87.ogg",
          "TranslationKey": "Characters/Dialogue/MarriageDialogueKrobus:Indoor_Night_3",
          "PageIndex": 0,
          "DisplayPattern": "Néha megállok és eltöprengek azon, hogy mit tanultam az emberekről tőled..."
        },
        {
          "DialogueFrom": "Marriage/Krobus/Indoor_Night_3",
          "DialogueText": "Bárcsak árnyékember társaim ismernék ezt az érzést.",
          "AudioPath": "assets/hu-HU/Krobus/88.ogg",
          "TranslationKey": "Characters/Dialogue/MarriageDialogueKrobus:Indoor_Night_3",
          "PageIndex": 1,
          "DisplayPattern": "Bárcsak árnyékember társaim ismernék ezt az érzést."
        },
        {
          "DialogueFrom": "Marriage/Krobus/Indoor_Night_4",
          "DialogueText": "Jó lakótársad akarok lenni, de sose tudom, hogy jól cselekszem-e... *morog* {Portrait:Sad}",
          "AudioPath": "assets/hu-HU/Krobus/89.ogg",
          "TranslationKey": "Characters/Dialogue/MarriageDialogueKrobus:Indoor_Night_4",
          "PageIndex": 0,
          "DisplayPattern": "Jó lakótársad akarok lenni, de sose tudom, hogy jól cselekszem-e... *morog*"
        },
        {
          "DialogueFrom": "Marriage/Krobus/Indoor_Night_4",
          "DialogueText": "Nehezen értem meg az emberek kifejezéseit. D... de... te boldog vagy velem?",
          "AudioPath": "assets/hu-HU/Krobus/90.ogg",
          "TranslationKey": "Characters/Dialogue/MarriageDialogueKrobus:Indoor_Night_4",
          "PageIndex": 1,
          "DisplayPattern": "Nehezen értem meg az emberek kifejezéseit. D... de... te boldog vagy velem?"
        },
        {
          "DialogueFrom": "Marriage/Krobus/Indoor_Night_4",
          "DialogueText": "Rendben! {Portrait:Custom:7}",
          "AudioPath": "assets/hu-HU/Krobus/91.ogg",
          "TranslationKey": "Characters/Dialogue/MarriageDialogueKrobus:Indoor_Night_4",
          "PageIndex": 2,
          "DisplayPattern": "Rendben!"
        },
        {
          "DialogueFrom": "Marriage/Krobus/Indoor_Night_Krobus",
          "DialogueText": "Üdv, {Farmer_Name}. Üdv itthon. Úgy látom, hogy elég keményen dolgoztál odakint! {Portrait:Happy}",
          "AudioPath": "assets/hu-HU/Krobus/92.ogg",
          "TranslationKey": "Characters/Dialogue/MarriageDialogueKrobus:Indoor_Night_Krobus",
          "PageIndex": 0,
          "DisplayPattern": "Üdv, . Üdv itthon. Úgy látom, hogy elég keményen dolgoztál odakint!"
        },
        {
          "DialogueFrom": "Marriage/Krobus/Neutral_0",
          "DialogueText": "Sose fogok megöregedni, de te igen. Néha ez elszomorít... de nincs baj. {Portrait:Sad}",
          "AudioPath": "assets/hu-HU/Krobus/93.ogg",
          "TranslationKey": "Characters/Dialogue/MarriageDialogueKrobus:Neutral_0",
          "PageIndex": 0,
          "DisplayPattern": "Sose fogok megöregedni, de te igen. Néha ez elszomorít... de nincs baj."
        },
        {
          "DialogueFrom": "Marriage/Krobus/Neutral_1",
          "DialogueText": "Szerinted nagyapád megengedte volna, hogy egy szörny éljen a házában?",
          "AudioPath": "assets/hu-HU/Krobus/94.ogg",
          "TranslationKey": "Characters/Dialogue/MarriageDialogueKrobus:Neutral_1",
          "PageIndex": 0,
          "DisplayPattern": "Szerinted nagyapád megengedte volna, hogy egy szörny éljen a házában?"
        },
        {
          "DialogueFrom": "Marriage/Krobus/Neutral_2",
          "DialogueText": "Szerinted bajba kerülhetünk attól, hogy együtt élünk? {Portrait:Sad}",
          "AudioPath": "assets/hu-HU/Krobus/95.ogg",
          "TranslationKey": "Characters/Dialogue/MarriageDialogueKrobus:Neutral_2",
          "PageIndex": 0,
          "DisplayPattern": "Szerinted bajba kerülhetünk attól, hogy együtt élünk?"
        },
        {
          "DialogueFrom": "Marriage/Krobus/Neutral_3",
          "DialogueText": "Itt olyan világos van... Lehet pár órára lehunyom a szemem. {Portrait:Sad}",
          "AudioPath": "assets/hu-HU/Krobus/96.ogg",
          "TranslationKey": "Characters/Dialogue/MarriageDialogueKrobus:Neutral_3",
          "PageIndex": 0,
          "DisplayPattern": "Itt olyan világos van... Lehet pár órára lehunyom a szemem."
        },
        {
          "DialogueFrom": "Marriage/Krobus/Neutral_4",
          "DialogueText": "Nem mehetek ki, csak bizonyos ételeket ehetek, bizonyos hőmérsékletet viselek csak el... Remélem nem túl nagy baj, hogy velem élsz, {Farmer_Name}. {Portrait:Sad}",
          "AudioPath": "assets/hu-HU/Krobus/97.ogg",
          "TranslationKey": "Characters/Dialogue/MarriageDialogueKrobus:Neutral_4",
          "PageIndex": 0,
          "DisplayPattern": "Nem mehetek ki, csak bizonyos ételeket ehetek, bizonyos hőmérsékletet viselek csak el... Remélem nem túl nagy baj, hogy velem élsz, ."
        },
        {
          "DialogueFrom": "Marriage/Krobus/Neutral_5",
          "DialogueText": "Welwick azt mondta, hogy ma meg vagyok átkozva. {Portrait:Sad}",
          "AudioPath": "assets/hu-HU/Krobus/98.ogg",
          "TranslationKey": "Characters/Dialogue/MarriageDialogueKrobus:Neutral_5",
          "PageIndex": 0,
          "DisplayPattern": "Welwick azt mondta, hogy ma meg vagyok átkozva."
        },
        {
          "DialogueFrom": "Marriage/Krobus/Neutral_6",
          "DialogueText": "Elmondok egy titkot... Én valójában nem alszom, csak lehunyt szemmel fekszem...",
          "AudioPath": "assets/hu-HU/Krobus/99.ogg",
          "TranslationKey": "Characters/Dialogue/MarriageDialogueKrobus:Neutral_6",
          "PageIndex": 0,
          "DisplayPattern": "Elmondok egy titkot... Én valójában nem alszom, csak lehunyt szemmel fekszem..."
        },
        {
          "DialogueFrom": "Marriage/Krobus/Neutral_7",
          "DialogueText": "Te elég fura vagy, hogy egy magamfajta lénnyel akarsz együtt élni.",
          "AudioPath": "assets/hu-HU/Krobus/100.ogg",
          "TranslationKey": "Characters/Dialogue/MarriageDialogueKrobus:Neutral_7",
          "PageIndex": 0,
          "DisplayPattern": "Te elég fura vagy, hogy egy magamfajta lénnyel akarsz együtt élni."
        },
        {
          "DialogueFrom": "Marriage/Krobus/Neutral_8",
          "DialogueText": "Ma egész nap takarítani fogok! Ez jó móka. {Portrait:Custom:7}",
          "AudioPath": "assets/hu-HU/Krobus/101.ogg",
          "TranslationKey": "Characters/Dialogue/MarriageDialogueKrobus:Neutral_8",
          "PageIndex": 0,
          "DisplayPattern": "Ma egész nap takarítani fogok! Ez jó móka."
        },
        {
          "DialogueFrom": "Marriage/Krobus/Neutral_9",
          "DialogueText": "Vajon egész életünket itt fogjuk leélni? A költözés talán túl veszélyes lenne számomra.",
          "AudioPath": "assets/hu-HU/Krobus/102.ogg",
          "TranslationKey": "Characters/Dialogue/MarriageDialogueKrobus:Neutral_9",
          "PageIndex": 0,
          "DisplayPattern": "Vajon egész életünket itt fogjuk leélni? A költözés talán túl veszélyes lenne számomra."
        },
        {
          "DialogueFrom": "Marriage/Krobus/NoBed_0",
          "DialogueText": "Mégis hol kellene aludnom...? {Portrait:Sad}",
          "AudioPath": "assets/hu-HU/Krobus/103.ogg",
          "TranslationKey": "Characters/Dialogue/MarriageDialogue:NoBed_0",
          "PageIndex": 0,
          "DisplayPattern": "Mégis hol kellene aludnom...?"
        },
        {
          "DialogueFrom": "Marriage/Krobus/NoBed_1",
          "DialogueText": "Tegnap este nem tudtam jól aludni... {Portrait:Sad}",
          "AudioPath": "assets/hu-HU/Krobus/104.ogg",
          "TranslationKey": "Characters/Dialogue/MarriageDialogue:NoBed_1",
          "PageIndex": 0,
          "DisplayPattern": "Tegnap este nem tudtam jól aludni..."
        },
        {
          "DialogueFrom": "Marriage/Krobus/NoBed_2",
          "DialogueText": "Tegnap este a padlón kellett aludnom... {Portrait:Sad}",
          "AudioPath": "assets/hu-HU/Krobus/105.ogg",
          "TranslationKey": "Characters/Dialogue/MarriageDialogue:NoBed_2",
          "PageIndex": 0,
          "DisplayPattern": "Tegnap este a padlón kellett aludnom..."
        },
        {
          "DialogueFrom": "Marriage/Krobus/NoBed_3",
          "DialogueText": "Történt valami az ágyunkkal...? {Portrait:Sad}",
          "AudioPath": "assets/hu-HU/Krobus/106.ogg",
          "TranslationKey": "Characters/Dialogue/MarriageDialogue:NoBed_3",
          "PageIndex": 0,
          "DisplayPattern": "Történt valami az ágyunkkal...?"
        },
        {
          "DialogueFrom": "Marriage/Krobus/OneKid_0",
          "DialogueText": "Te és %kid1 tudtatok ma játszani?",
          "AudioPath": "assets/hu-HU/Krobus/107.ogg",
          "TranslationKey": "Characters/Dialogue/MarriageDialogue:OneKid_0",
          "PageIndex": 0,
          "DisplayPattern": "Te és tudtatok ma játszani?"
        },
        {
          "DialogueFrom": "Marriage/Krobus/OneKid_1",
          "DialogueText": "Vajon ha %kid1 felnő, akkor belőle is gazda lesz, mint belőled?",
          "AudioPath": "assets/hu-HU/Krobus/108.ogg",
          "TranslationKey": "Characters/Dialogue/MarriageDialogue:OneKid_1",
          "PageIndex": 0,
          "DisplayPattern": "Vajon ha felnő, akkor belőle is gazda lesz, mint belőled?"
        },
        {
          "DialogueFrom": "Marriage/Krobus/OneKid_2",
          "DialogueText": "Ne aggódj, majd megetetem %kid1-t. Te csak koncentrálj a farm üzemeltetésére.",
          "AudioPath": "assets/hu-HU/Krobus/109.ogg",
          "TranslationKey": "Characters/Dialogue/MarriageDialogue:OneKid_2",
          "PageIndex": 0,
          "DisplayPattern": "Ne aggódj, majd megetetem -t. Te csak koncentrálj a üzemeltetésére."
        },
        {
          "DialogueFrom": "Marriage/Krobus/OneKid_3",
          "DialogueText": "Nem tudom, hogy hogyan, de Yoba megáldotta ezt a házat egy 'gyermekkel'...",
          "AudioPath": "assets/hu-HU/Krobus/110.ogg",
          "TranslationKey": "Characters/Dialogue/MarriageDialogueKrobus:OneKid_3",
          "PageIndex": 0,
          "DisplayPattern": "Nem tudom, hogy hogyan, de Yoba megáldotta ezt a házat egy 'gyermekkel'..."
        },
        {
          "DialogueFrom": "Marriage/Krobus/Outdoor_0",
          "DialogueText": "Egy kicsit idekint maradok, de óvatosnak kell lennünk... ha valaki jönne, akkor el kell bújnom!",
          "AudioPath": "assets/hu-HU/Krobus/111.ogg",
          "TranslationKey": "Characters/Dialogue/MarriageDialogueKrobus:Outdoor_0",
          "PageIndex": 0,
          "DisplayPattern": "Egy kicsit idekint maradok, de óvatosnak kell lennünk... ha valaki jönne, akkor el kell bújnom!"
        },
        {
          "DialogueFrom": "Marriage/Krobus/Outdoor_1",
          "DialogueText": "Ritka az az alkalom, mikor kiléphetek a szabadba!",
          "AudioPath": "assets/hu-HU/Krobus/112.ogg",
          "TranslationKey": "Characters/Dialogue/MarriageDialogueKrobus:Outdoor_1",
          "PageIndex": 0,
          "DisplayPattern": "Ritka az az alkalom, mikor kiléphetek a szabadba!"
        },
        {
          "DialogueFrom": "Marriage/Krobus/Outdoor_2",
          "DialogueText": "Micsoda csodálatos nap! {Portrait:Happy}",
          "AudioPath": "assets/hu-HU/Krobus/113.ogg",
          "TranslationKey": "Characters/Dialogue/MarriageDialogueKrobus:Outdoor_2",
          "PageIndex": 0,
          "DisplayPattern": "Micsoda csodálatos nap!"
        },
        {
          "DialogueFrom": "Marriage/Krobus/Outdoor_3",
          "DialogueText": "A nagy és nyílt terek feszültté tesznek... {Portrait:Sad}",
          "AudioPath": "assets/hu-HU/Krobus/114.ogg",
          "TranslationKey": "Characters/Dialogue/MarriageDialogueKrobus:Outdoor_3",
          "PageIndex": 0,
          "DisplayPattern": "A nagy és nyílt terek feszültté tesznek..."
        },
        {
          "DialogueFrom": "Marriage/Krobus/Outdoor_4",
          "DialogueText": "Kérlek csak tedd a dolgodat, addig én itt maradok és őrzöm a házat.",
          "AudioPath": "assets/hu-HU/Krobus/115.ogg",
          "TranslationKey": "Characters/Dialogue/MarriageDialogueKrobus:Outdoor_4",
          "PageIndex": 0,
          "DisplayPattern": "Kérlek csak tedd a dolgodat, addig én itt maradok és őrzöm a házat."
        },
        {
          "DialogueFrom": "Marriage/Krobus/Outdoor_Krobus",
          "DialogueText": "Itt várok egy kicsit, hátha jönnek majd a rovarok.",
          "AudioPath": "assets/hu-HU/Krobus/116.ogg",
          "TranslationKey": "Characters/Dialogue/MarriageDialogueKrobus:Outdoor_Krobus",
          "PageIndex": 0,
          "DisplayPattern": "Itt várok egy kicsit, hátha jönnek majd a rovarok."
        },
        {
          "DialogueFrom": "Marriage/Krobus/Outdoor_Krobus",
          "DialogueText": "Még nem reggeliztem!",
          "AudioPath": "assets/hu-HU/Krobus/117.ogg",
          "TranslationKey": "Characters/Dialogue/MarriageDialogueKrobus:Outdoor_Krobus",
          "PageIndex": 1,
          "DisplayPattern": "Még nem reggeliztem!"
        },
        {
          "DialogueFrom": "Marriage/Krobus/Rainy_Day_0",
          "DialogueText": "Te is annyira szereted az esős napokat mint én, {Farmer_Name}?",
          "AudioPath": "assets/hu-HU/Krobus/118.ogg",
          "TranslationKey": "Characters/Dialogue/MarriageDialogueKrobus:Rainy_Day_0",
          "PageIndex": 0,
          "DisplayPattern": "Te is annyira szereted az esős napokat mint én, ?"
        },
        {
          "DialogueFrom": "Marriage/Krobus/Rainy_Day_1",
          "DialogueText": "Oly sokmindenben különbözünk... de ez így van rendjén.",
          "AudioPath": "assets/hu-HU/Krobus/119.ogg",
          "TranslationKey": "Characters/Dialogue/MarriageDialogueKrobus:Rainy_Day_1",
          "PageIndex": 0,
          "DisplayPattern": "Oly sokmindenben különbözünk... de ez így van rendjén."
        },
        {
          "DialogueFrom": "Marriage/Krobus/Rainy_Day_2",
          "DialogueText": "Jó reggelt, {Farmer_Name}! Ma korán keltem és ezt találtam odakint neked. [305 308 203 795 397]",
          "AudioPath": "assets/hu-HU/Krobus/120.ogg",
          "TranslationKey": "Characters/Dialogue/MarriageDialogueKrobus:Rainy_Day_2",
          "PageIndex": 0,
          "DisplayPattern": "Jó reggelt, ! Ma korán keltem és ezt találtam odakint neked."
        },
        {
          "DialogueFrom": "Marriage/Krobus/Rainy_Day_2",
          "DialogueText": "Remélem ez nem túl fura.",
          "AudioPath": "assets/hu-HU/Krobus/121.ogg",
          "TranslationKey": "Characters/Dialogue/MarriageDialogueKrobus:Rainy_Day_2",
          "PageIndex": 1,
          "DisplayPattern": "Remélem ez nem túl fura."
        },
        {
          "DialogueFrom": "Marriage/Krobus/Rainy_Day_3",
          "DialogueText": "Vajon a varázsló tud... erről? Remélem sikerül titokban tartania. {Portrait:Sad}",
          "AudioPath": "assets/hu-HU/Krobus/122.ogg",
          "TranslationKey": "Characters/Dialogue/MarriageDialogueKrobus:Rainy_Day_3",
          "PageIndex": 0,
          "DisplayPattern": "Vajon a varázsló tud... erről? Remélem sikerül titokban tartania."
        },
        {
          "DialogueFrom": "Marriage/Krobus/Rainy_Day_4",
          "DialogueText": "Akármennyire is próbálok civilizált lenni, néha muszáj csintalannak lennem... {Portrait:Custom:6}",
          "AudioPath": "assets/hu-HU/Krobus/123.ogg",
          "TranslationKey": "Characters/Dialogue/MarriageDialogueKrobus:Rainy_Day_4",
          "PageIndex": 0,
          "DisplayPattern": "Akármennyire is próbálok civilizált lenni, néha muszáj csintalannak lennem..."
        },
        {
          "DialogueFrom": "Marriage/Krobus/Rainy_Day_4",
          "DialogueText": "Azt mondják, hogy ez a népem egyik lételeme.",
          "AudioPath": "assets/hu-HU/Krobus/124.ogg",
          "TranslationKey": "Characters/Dialogue/MarriageDialogueKrobus:Rainy_Day_4",
          "PageIndex": 1,
          "DisplayPattern": "Azt mondják, hogy ez a népem egyik lételeme."
        },
        {
          "DialogueFrom": "Marriage/Krobus/Rainy_Day_Krobus",
          "DialogueText": "Áh, az eső miatt sokkal nagyobb a pára... Sokkal kényelmesebben érzem magam.",
          "AudioPath": "assets/hu-HU/Krobus/125.ogg",
          "TranslationKey": "Characters/Dialogue/MarriageDialogueKrobus:Rainy_Day_Krobus",
          "PageIndex": 0,
          "DisplayPattern": "Áh, az eső miatt sokkal nagyobb a pára... Sokkal kényelmesebben érzem magam."
        },
        {
          "DialogueFrom": "Marriage/Krobus/Rainy_Night_0",
          "DialogueText": "Az ilyen éjszakákon azok, akik kinéznek az ablakon gyakran látnak árnyékalakokat. Így belegondolva... akár én is lehettem volna. {Portrait:Custom:7}",
          "AudioPath": "assets/hu-HU/Krobus/126.ogg",
          "TranslationKey": "Characters/Dialogue/MarriageDialogueKrobus:Rainy_Night_0",
          "PageIndex": 0,
          "DisplayPattern": "Az ilyen éjszakákon azok, akik kinéznek az ablakon gyakran látnak árnyékalakokat. Így belegondolva... akár én is lehettem volna."
        },
        {
          "DialogueFrom": "Marriage/Krobus/Rainy_Night_1",
          "DialogueText": "Ha a többi árnyékember tudna a közös együttélésünkről, akkor... 'megbüntetnének' engem. {Portrait:Sad}",
          "AudioPath": "assets/hu-HU/Krobus/127.ogg",
          "TranslationKey": "Characters/Dialogue/MarriageDialogueKrobus:Rainy_Night_1",
          "PageIndex": 0,
          "DisplayPattern": "Ha a többi árnyékember tudna a közös együttélésünkről, akkor... 'megbüntetnének' engem."
        },
        {
          "DialogueFrom": "Marriage/Krobus/Rainy_Night_1",
          "DialogueText": "Tudod, a legtöbben megvetik az embereket.",
          "AudioPath": "assets/hu-HU/Krobus/128.ogg",
          "TranslationKey": "Characters/Dialogue/MarriageDialogueKrobus:Rainy_Night_1",
          "PageIndex": 1,
          "DisplayPattern": "Tudod, a legtöbben megvetik az embereket."
        },
        {
          "DialogueFrom": "Marriage/Krobus/Rainy_Night_2",
          "DialogueText": "Teljesen el vagy ázva, és ki vagy hűlve! Ez nem veszélyes a te fajtádra nézve? {Portrait:Sad}",
          "AudioPath": "assets/hu-HU/Krobus/129.ogg",
          "TranslationKey": "Characters/Dialogue/MarriageDialogueKrobus:Rainy_Night_2",
          "PageIndex": 0,
          "DisplayPattern": "Teljesen el vagy ázva, és ki vagy hűlve! Ez nem veszélyes a te fajtádra nézve?"
        },
        {
          "DialogueFrom": "Marriage/Krobus/Rainy_Night_3",
          "DialogueText": "Már vacsoráztam, de nem olyat, amit te is ehetnél... sajnálom.",
          "AudioPath": "assets/hu-HU/Krobus/130.ogg",
          "TranslationKey": "Characters/Dialogue/MarriageDialogueKrobus:Rainy_Night_3",
          "PageIndex": 0,
          "DisplayPattern": "Már vacsoráztam, de nem olyat, amit te is ehetnél... sajnálom."
        },
        {
          "DialogueFrom": "Marriage/Krobus/Rainy_Night_4",
          "DialogueText": "Amióta elhagytam a népemet, egy új otthon után kutattam... és most tartozom valahová. Ez sokat jelent nekem.",
          "AudioPath": "assets/hu-HU/Krobus/131.ogg",
          "TranslationKey": "Characters/Dialogue/MarriageDialogueKrobus:Rainy_Night_4",
          "PageIndex": 0,
          "DisplayPattern": "Amióta elhagytam a népemet, egy új otthon után kutattam... és most tartozom valahová. Ez sokat jelent nekem."
        },
        {
          "DialogueFrom": "Marriage/Krobus/Rainy_Night_5",
          "DialogueText": "Azt beszélik, hogy a népem régen jött ide, mikor egy nagy katasztrófa miatt az űrbeli lelkek átjuthattak a fizikai síkba.",
          "AudioPath": "assets/hu-HU/Krobus/132.ogg",
          "TranslationKey": "Characters/Dialogue/MarriageDialogueKrobus:Rainy_Night_5",
          "PageIndex": 0,
          "DisplayPattern": "Azt beszélik, hogy a népem régen jött ide, mikor egy nagy katasztrófa miatt az űrbeli lelkek átjuthattak a fizikai síkba."
        },
        {
          "DialogueFrom": "Marriage/Krobus/Rainy_Night_Krobus",
          "DialogueText": "Az eső hangja a csatornákra emlékeztet... megnyugtató.",
          "AudioPath": "assets/hu-HU/Krobus/133.ogg",
          "TranslationKey": "Characters/Dialogue/MarriageDialogueKrobus:Rainy_Night_Krobus",
          "PageIndex": 0,
          "DisplayPattern": "Az eső hangja a csatornákra emlékeztet... megnyugtató."
        },
        {
          "DialogueFrom": "Marriage/Krobus/Rainy_Night_Krobus",
          "DialogueText": "A csatorna volt a menedékem... Ott biztonságban éreztem magam. De ne aggódj... Ugyanezt érzem az új otthonommal kapcsolatban is.",
          "AudioPath": "assets/hu-HU/Krobus/134.ogg",
          "TranslationKey": "Characters/Dialogue/MarriageDialogueKrobus:Rainy_Night_Krobus",
          "PageIndex": 1,
          "DisplayPattern": "A csatorna volt a menedékem... Ott biztonságban éreztem magam. De ne aggódj... Ugyanezt érzem az új otthonommal kapcsolatban is."
        },
        {
          "DialogueFrom": "Marriage/Krobus/spouseRoom_Krobus",
          "DialogueText": "Fizikailag annyira különbözőek vagyunk, hogy igazi kihívás az együttélés, nemde?",
          "AudioPath": "assets/hu-HU/Krobus/135.ogg",
          "TranslationKey": "Characters/Dialogue/MarriageDialogueKrobus:spouseRoom_Krobus",
          "PageIndex": 0,
          "DisplayPattern": "Fizikailag annyira különbözőek vagyunk, hogy igazi kihívás az együttélés, nemde?"
        },
        {
          "DialogueFrom": "Marriage/Krobus/spouseRoom_Krobus",
          "DialogueText": "$e",
          "AudioPath": "assets/hu-HU/Krobus/136.ogg",
          "TranslationKey": "Characters/Dialogue/MarriageDialogueKrobus:spouseRoom_Krobus",
          "PageIndex": 1,
          "DisplayPattern": "$e"
        },
        {
          "DialogueFrom": "Marriage/Krobus/spouseRoom_Krobus",
          "DialogueText": "Remélem nem zavar téged ez a pára. Mindketten kompromisszumokat kell kötnünk, ha együtt akarunk élni!",
          "AudioPath": "assets/hu-HU/Krobus/137.ogg",
          "TranslationKey": "Characters/Dialogue/MarriageDialogueKrobus:spouseRoom_Krobus",
          "PageIndex": 2,
          "DisplayPattern": "Remélem nem zavar téged ez a pára. Mindketten kompromisszumokat kell kötnünk, ha együtt akarunk élni!"
        },
        {
          "DialogueFrom": "Marriage/Krobus/spring_1",
          "DialogueText": "Mik a terveid az új évre nézve, {Farmer_Name}?",
          "AudioPath": "assets/hu-HU/Krobus/138.ogg",
          "TranslationKey": "Characters/Dialogue/MarriageDialogueKrobus:spring_1",
          "PageIndex": 0,
          "DisplayPattern": "Mik a terveid az új évre nézve, ?"
        },
        {
          "DialogueFrom": "Marriage/Krobus/spring_12",
          "DialogueText": "...",
          "AudioPath": "assets/hu-HU/Krobus/139.ogg",
          "TranslationKey": "Characters/Dialogue/MarriageDialogueKrobus:spring_12",
          "PageIndex": 0,
          "DisplayPattern": "..."
        },
        {
          "DialogueFrom": "Marriage/Krobus/spring_19",
          "DialogueText": "...",
          "AudioPath": "assets/hu-HU/Krobus/140.ogg",
          "TranslationKey": "Characters/Dialogue/MarriageDialogueKrobus:spring_19",
          "PageIndex": 0,
          "DisplayPattern": "..."
        },
        {
          "DialogueFrom": "Marriage/Krobus/spring_23",
          "DialogueText": "Menj el a holnapi virágtáncra! Ne aggódj miattam.",
          "AudioPath": "assets/hu-HU/Krobus/141.ogg",
          "TranslationKey": "Characters/Dialogue/MarriageDialogueKrobus:spring_23",
          "PageIndex": 0,
          "DisplayPattern": "Menj el a holnapi virágtáncra! Ne aggódj miattam."
        },
        {
          "DialogueFrom": "Marriage/Krobus/spring_26",
          "DialogueText": "...",
          "AudioPath": "assets/hu-HU/Krobus/142.ogg",
          "TranslationKey": "Characters/Dialogue/MarriageDialogueKrobus:spring_26",
          "PageIndex": 0,
          "DisplayPattern": "..."
        },
        {
          "DialogueFrom": "Marriage/Krobus/spring_5",
          "DialogueText": "...",
          "AudioPath": "assets/hu-HU/Krobus/143.ogg",
          "TranslationKey": "Characters/Dialogue/MarriageDialogueKrobus:spring_5",
          "PageIndex": 0,
          "DisplayPattern": "..."
        },
        {
          "DialogueFrom": "Marriage/Krobus/spring_8",
          "DialogueText": "Most, hogy vége van a télnek, rengeteg hasznos időnek nézünk elébe.",
          "AudioPath": "assets/hu-HU/Krobus/144.ogg",
          "TranslationKey": "Characters/Dialogue/MarriageDialogue:spring_8",
          "PageIndex": 0,
          "DisplayPattern": "Most, hogy vége van a télnek, rengeteg hasznos időnek nézünk elébe."
        },
        {
          "DialogueFrom": "Marriage/Krobus/spring_Krobus",
          "DialogueText": "Most 'tavasz' van, ugye? Érzem a vad torma borsos aromáját.",
          "AudioPath": "assets/hu-HU/Krobus/145.ogg",
          "TranslationKey": "Characters/Dialogue/MarriageDialogueKrobus:spring_Krobus",
          "PageIndex": 0,
          "DisplayPattern": "Most 'tavasz' van, ugye? Érzem a vad torma borsos aromáját."
        },
        {
          "DialogueFrom": "Marriage/Krobus/summer_1",
          "DialogueText": "Könnyedén leégek a napon, szóval óvatosnak kell lennem az év ezen szakaszában.",
          "AudioPath": "assets/hu-HU/Krobus/146.ogg",
          "TranslationKey": "Characters/Dialogue/MarriageDialogueKrobus:summer_1",
          "PageIndex": 0,
          "DisplayPattern": "Könnyedén leégek a napon, szóval óvatosnak kell lennem az év ezen szakaszában."
        },
        {
          "DialogueFrom": "Marriage/Krobus/summer_12",
          "DialogueText": "...",
          "AudioPath": "assets/hu-HU/Krobus/147.ogg",
          "TranslationKey": "Characters/Dialogue/MarriageDialogueKrobus:summer_12",
          "PageIndex": 0,
          "DisplayPattern": "..."
        },
        {
          "DialogueFrom": "Marriage/Krobus/summer_15",
          "DialogueText": "Nyár van... vagyis a ház tele van legyekkel.",
          "AudioPath": "assets/hu-HU/Krobus/148.ogg",
          "TranslationKey": "Characters/Dialogue/MarriageDialogueKrobus:summer_15",
          "PageIndex": 0,
          "DisplayPattern": "Nyár van... vagyis a ház tele van legyekkel."
        },
        {
          "DialogueFrom": "Marriage/Krobus/summer_15",
          "DialogueText": "Ne aggódj, majd én elintézem őket. Jó proteinként szolgálnak! {Portrait:Happy}",
          "AudioPath": "assets/hu-HU/Krobus/149.ogg",
          "TranslationKey": "Characters/Dialogue/MarriageDialogueKrobus:summer_15",
          "PageIndex": 1,
          "DisplayPattern": "Ne aggódj, majd én elintézem őket. Jó proteinként szolgálnak!"
        },
        {
          "DialogueFrom": "Marriage/Krobus/summer_19",
          "DialogueText": "...",
          "AudioPath": "assets/hu-HU/Krobus/150.ogg",
          "TranslationKey": "Characters/Dialogue/MarriageDialogueKrobus:summer_19",
          "PageIndex": 0,
          "DisplayPattern": "..."
        },
        {
          "DialogueFrom": "Marriage/Krobus/summer_26",
          "DialogueText": "...",
          "AudioPath": "assets/hu-HU/Krobus/151.ogg",
          "TranslationKey": "Characters/Dialogue/MarriageDialogueKrobus:summer_26",
          "PageIndex": 0,
          "DisplayPattern": "..."
        },
        {
          "DialogueFrom": "Marriage/Krobus/summer_5",
          "DialogueText": "...",
          "AudioPath": "assets/hu-HU/Krobus/152.ogg",
          "TranslationKey": "Characters/Dialogue/MarriageDialogueKrobus:summer_5",
          "PageIndex": 0,
          "DisplayPattern": "..."
        },
        {
          "DialogueFrom": "Marriage/Krobus/summer_8",
          "DialogueText": "Mmm... mi ez a csodálatos illat? Biztos egész este izzadtál... {Portrait:Happy}",
          "AudioPath": "assets/hu-HU/Krobus/153.ogg",
          "TranslationKey": "Characters/Dialogue/MarriageDialogueKrobus:summer_8",
          "PageIndex": 0,
          "DisplayPattern": "Mmm... mi ez a csodálatos illat? Biztos egész este izzadtál..."
        },
        {
          "DialogueFrom": "Marriage/Krobus/summer_Krobus",
          "DialogueText": "Az év ezen időszakát 'nyárnak' nevezitek, ugye? Jó a hőség és a páratartalom, de bár ne legyen ennyire napos az idő.",
          "AudioPath": "assets/hu-HU/Krobus/154.ogg",
          "TranslationKey": "Characters/Dialogue/MarriageDialogueKrobus:summer_Krobus",
          "PageIndex": 0,
          "DisplayPattern": "Az év ezen időszakát 'nyárnak' nevezitek, ugye? Jó a hőség és a páratartalom, de bár ne legyen ennyire napos az idő."
        },
        {
          "DialogueFrom": "Marriage/Krobus/TwoKids_0",
          "DialogueText": "Ne aggódj... %kid1 és %kid2 már kapott űrtojás omlettet.",
          "AudioPath": "assets/hu-HU/Krobus/155.ogg",
          "TranslationKey": "Characters/Dialogue/MarriageDialogueKrobus:TwoKids_0",
          "PageIndex": 0,
          "DisplayPattern": "Ne aggódj... és már kapott űrtojás omlettet."
        },
        {
          "DialogueFrom": "Marriage/Krobus/TwoKids_1",
          "DialogueText": "kid1 több figyelmet érdemelne tőlünk most, hogy %kid2 is itt van. Nem akarjuk, hogy irigyek legyenek egymásra.",
          "AudioPath": "assets/hu-HU/Krobus/156.ogg",
          "TranslationKey": "Characters/Dialogue/MarriageDialogue:TwoKids_1",
          "PageIndex": 0,
          "DisplayPattern": "több figyelmet érdemelne tőlünk most, hogy is itt van. Nem akarjuk, hogy irigyek legyenek egymásra."
        },
        {
          "DialogueFrom": "Marriage/Krobus/TwoKids_2",
          "DialogueText": "Aggódom a gyerekek jövője miatt... De bízom abban, hogy Yobanak tervei vannak velük.",
          "AudioPath": "assets/hu-HU/Krobus/157.ogg",
          "TranslationKey": "Characters/Dialogue/MarriageDialogueKrobus:TwoKids_2",
          "PageIndex": 0,
          "DisplayPattern": "Aggódom a gyerekek jövője miatt... De bízom abban, hogy Yobanak tervei vannak velük."
        },
        {
          "DialogueFrom": "Marriage/Krobus/TwoKids_3",
          "DialogueText": "Ezt a házat már két gyerekkel áldották meg... Vagyis akkor Yoba jóváhagyja szokatlan életmódunkat?",
          "AudioPath": "assets/hu-HU/Krobus/158.ogg",
          "TranslationKey": "Characters/Dialogue/MarriageDialogueKrobus:TwoKids_3",
          "PageIndex": 0,
          "DisplayPattern": "Ezt a házat már két gyerekkel áldották meg... Vagyis akkor Yoba jóváhagyja szokatlan életmódunkat?"
        },
        {
          "DialogueFrom": "Marriage/Krobus/winter_1",
          "DialogueText": "Brrr.... Hideg van. Azt hiszem megjött a tél.",
          "AudioPath": "assets/hu-HU/Krobus/159.ogg",
          "TranslationKey": "Characters/Dialogue/MarriageDialogue:winter_1",
          "PageIndex": 0,
          "DisplayPattern": "Brrr.... Hideg van. Azt hiszem megjött a tél."
        },
        {
          "DialogueFrom": "Marriage/Krobus/winter_12",
          "DialogueText": "...",
          "AudioPath": "assets/hu-HU/Krobus/160.ogg",
          "TranslationKey": "Characters/Dialogue/MarriageDialogueKrobus:winter_12",
          "PageIndex": 0,
          "DisplayPattern": "..."
        },
        {
          "DialogueFrom": "Marriage/Krobus/winter_19",
          "DialogueText": "...",
          "AudioPath": "assets/hu-HU/Krobus/161.ogg",
          "TranslationKey": "Characters/Dialogue/MarriageDialogueKrobus:winter_19",
          "PageIndex": 0,
          "DisplayPattern": "..."
        },
        {
          "DialogueFrom": "Marriage/Krobus/winter_26",
          "DialogueText": "...",
          "AudioPath": "assets/hu-HU/Krobus/162.ogg",
          "TranslationKey": "Characters/Dialogue/MarriageDialogueKrobus:winter_26",
          "PageIndex": 0,
          "DisplayPattern": "..."
        },
        {
          "DialogueFrom": "Marriage/Krobus/winter_28",
          "DialogueText": "Köszönöm, hogy itt lehetek, {Farmer_Name}. Alig várom az újabb nagyszerű évet! {Portrait:Happy}",
          "AudioPath": "assets/hu-HU/Krobus/163.ogg",
          "TranslationKey": "Characters/Dialogue/MarriageDialogueKrobus:winter_28",
          "PageIndex": 0,
          "DisplayPattern": "Köszönöm, hogy itt lehetek, . Alig várom az újabb nagyszerű évet!"
        },
        {
          "DialogueFrom": "Marriage/Krobus/winter_5",
          "DialogueText": "...",
          "AudioPath": "assets/hu-HU/Krobus/164.ogg",
          "TranslationKey": "Characters/Dialogue/MarriageDialogueKrobus:winter_5",
          "PageIndex": 0,
          "DisplayPattern": "..."
        },
        {
          "DialogueFrom": "Marriage/Krobus/winter_7",
          "DialogueText": "Benevezel a holnapi horgászós versenyre?",
          "AudioPath": "assets/hu-HU/Krobus/165.ogg",
          "TranslationKey": "Characters/Dialogue/MarriageDialogue:winter_7",
          "PageIndex": 0,
          "DisplayPattern": "Benevezel a holnapi horgászós versenyre?"
        },
        {
          "DialogueFrom": "Marriage/Krobus/winter_Krobus",
          "DialogueText": "Az év mostani szakaszában lévő sötétség nagyon nyugtató. Bárcsak melegebb volna!",
          "AudioPath": "assets/hu-HU/Krobus/166.ogg",
          "TranslationKey": "Characters/Dialogue/MarriageDialogueKrobus:winter_Krobus",
          "PageIndex": 0,
          "DisplayPattern": "Az év mostani szakaszában lévő sötétség nagyon nyugtató. Bárcsak melegebb volna!"
        },
        {
          "DialogueFrom": "rainy",
          "DialogueText": "Áh, a csatorna most nagyon gyorsan folyik. Hamarosan jó párás lesz itt a levegő... Pont ahogyan szeretem.",
          "AudioPath": "assets/hu-HU/Krobus/167.ogg",
          "TranslationKey": "Characters/Dialogue/rainy:Krobus",
          "PageIndex": 0,
          "DisplayPattern": "Áh, a csatorna most nagyon gyorsan folyik. Hamarosan jó párás lesz itt a levegő... Pont ahogyan szeretem."
        },
        {
          "DialogueFrom": "Event:Sewer/691039:s0",
          "DialogueText": "If you dwarves hadn't driven us from our ancestral home, we'd never have had to resort to violence!",
          "AudioPath": "assets/hu-HU/Krobus/168.ogg",
          "TranslationKey": "Events/Sewer:691039:s0",
          "PageIndex": 0,
          "DisplayPattern": "If you dwarves hadn't driven us from our ancestral home, we'd never have had to resort to violence!"
        },
        {
          "DialogueFrom": "Event:Sewer/691039:s1",
          "DialogueText": "I'm sorry about your family.",
          "AudioPath": "assets/hu-HU/Krobus/169.ogg",
          "TranslationKey": "Events/Sewer:691039:s1",
          "PageIndex": 0,
          "DisplayPattern": "I'm sorry about your family."
        },
        {
          "DialogueFrom": "Event:Sewer/691039:s2",
          "DialogueText": "Come and get it, shrimpy.",
          "AudioPath": "assets/hu-HU/Krobus/170.ogg",
          "TranslationKey": "Events/Sewer:691039:s2",
          "PageIndex": 0,
          "DisplayPattern": "Come and get it, shrimpy."
        },
        {
          "DialogueFrom": "Event:Sewer/691039:s3",
          "DialogueText": "...And I'm truly sorry about the past, Dwarf. I have no personal gripe with you.",
          "AudioPath": "assets/hu-HU/Krobus/171.ogg",
          "TranslationKey": "Events/Sewer:691039:s3",
          "PageIndex": 0,
          "DisplayPattern": "...And I'm truly sorry about the past, Dwarf. I have no personal gripe with you."
        },
        {
          "DialogueFrom": "Festival/fall27/Krobus_y2",
          "DialogueText": "T-te meg mit keresel itt? {Portrait:Neutral}",
          "AudioPath": "assets/hu-HU/Krobus/172.ogg",
          "TranslationKey": "Data/Festivals/fall27:Krobus_y2",
          "PageIndex": 0,
          "DisplayPattern": "T-te meg mit keresel itt?"
        },
        {
          "DialogueFrom": "NPCGiftTastes/Krobus:s0",
          "DialogueText": "Ez egy lenyűgöző ajándék. A népemnek nagy megtiszteltetés ilyet ajándékba kapni.",
          "AudioPath": "assets/hu-HU/Krobus/173.ogg",
          "TranslationKey": "Data/NPCGiftTastes:Krobus:s0",
          "PageIndex": 0,
          "DisplayPattern": "Ez egy lenyűgöző ajándék. A népemnek nagy megtiszteltetés ilyet ajándékba kapni."
        },
        {
          "DialogueFrom": "NPCGiftTastes/Krobus:s1",
          "DialogueText": "Nagyon szépen köszönöm.",
          "AudioPath": "assets/hu-HU/Krobus/174.ogg",
          "TranslationKey": "Data/NPCGiftTastes:Krobus:s1",
          "PageIndex": 0,
          "DisplayPattern": "Nagyon szépen köszönöm."
        },
        {
          "DialogueFrom": "NPCGiftTastes/Krobus:s2",
          "DialogueText": "Az embereknek... érdekes az ízlésük.",
          "AudioPath": "assets/hu-HU/Krobus/175.ogg",
          "TranslationKey": "Data/NPCGiftTastes:Krobus:s2",
          "PageIndex": 0,
          "DisplayPattern": "Az embereknek... érdekes az ízlésük."
        },
        {
          "DialogueFrom": "NPCGiftTastes/Krobus:s3",
          "DialogueText": "Ó... Őőő. Azt hiszem ezt elfogadom.",
          "AudioPath": "assets/hu-HU/Krobus/176.ogg",
          "TranslationKey": "Data/NPCGiftTastes:Krobus:s3",
          "PageIndex": 0,
          "DisplayPattern": "Ó... Őőő. Azt hiszem ezt elfogadom."
        },
        {
          "DialogueFrom": "NPCGiftTastes/Krobus:s4",
          "DialogueText": "Köszönöm.",
          "AudioPath": "assets/hu-HU/Krobus/177.ogg",
          "TranslationKey": "Data/NPCGiftTastes:Krobus:s4",
          "PageIndex": 0,
          "DisplayPattern": "Köszönöm."
        },
        {
          "DialogueFrom": "MovieReactions/Krobus_fall_movie_0_BeforeMovie",
          "DialogueText": "Psszt... Hé, én vagyok az, Krobus. Felismersz? {Portrait:Custom:8}",
          "AudioPath": "assets/hu-HU/Krobus/178.ogg",
          "TranslationKey": "Strings/MovieReactions:Krobus_fall_movie_0_BeforeMovie",
          "PageIndex": 0,
          "DisplayPattern": "Psszt... Hé, én vagyok az, Krobus. Felismersz?"
        },
        {
          "DialogueFrom": "MovieReactions/Krobus_fall_movie_0_BeforeMovie",
          "DialogueText": "Ha valaki közeledne, akkor te beszélsz, oké? {Portrait:Custom:8}",
          "AudioPath": "assets/hu-HU/Krobus/179.ogg",
          "TranslationKey": "Strings/MovieReactions:Krobus_fall_movie_0_BeforeMovie",
          "PageIndex": 1,
          "DisplayPattern": "Ha valaki közeledne, akkor te beszélsz, oké?"
        },
        {
          "DialogueFrom": "MovieReactions/Krobus_fall_movie_0_DuringMovie",
          "DialogueText": "Nem minden árnyékember ilyen! {Portrait:Custom:8}",
          "AudioPath": "assets/hu-HU/Krobus/180.ogg",
          "TranslationKey": "Strings/MovieReactions:Krobus_fall_movie_0_DuringMovie",
          "PageIndex": 0,
          "DisplayPattern": "Nem minden árnyékember ilyen!"
        },
        {
          "DialogueFrom": "MovieReactions/Krobus_fall_movie_0_DuringMovie_2",
          "DialogueText": "Krobus párolog...",
          "AudioPath": "assets/hu-HU/Krobus/181.ogg",
          "TranslationKey": "Strings/MovieReactions:Krobus_fall_movie_0_DuringMovie_2",
          "PageIndex": 0,
          "DisplayPattern": "Krobus párolog..."
        },
        {
          "DialogueFrom": "MovieReactions/Krobus_fall_movie_0_AfterMovie",
          "DialogueText": "Nem vagyok hozzászokva a ruházatokhoz... Nagyon kényelmetlen! {Portrait:Custom:8}",
          "AudioPath": "assets/hu-HU/Krobus/182.ogg",
          "TranslationKey": "Strings/MovieReactions:Krobus_fall_movie_0_AfterMovie",
          "PageIndex": 0,
          "DisplayPattern": "Nem vagyok hozzászokva a ruházatokhoz... Nagyon kényelmetlen!"
        },
        {
          "DialogueFrom": "MovieReactions/Krobus_*_BeforeMovie",
          "DialogueText": "*köhöm*... Üdv! Nagyon izgatott vagyok, hogy a vizuális szórakoztató központban lehetek és pattogó kukoricát ehetek... akárcsak te! {Portrait:Custom:8}",
          "AudioPath": "assets/hu-HU/Krobus/183.ogg",
          "TranslationKey": "Strings/MovieReactions:Krobus_*_BeforeMovie",
          "PageIndex": 0,
          "DisplayPattern": "*köhöm*... Üdv! Nagyon izgatott vagyok, hogy a vizuális szórakoztató központban lehetek és pattogó kukoricát ehetek... akárcsak te!"
        },
        {
          "DialogueFrom": "MovieReactions/Krobus_*_BeforeMovie",
          "DialogueText": "*suttogva*... milyen vagyok? {Portrait:Custom:8}",
          "AudioPath": "assets/hu-HU/Krobus/184.ogg",
          "TranslationKey": "Strings/MovieReactions:Krobus_*_BeforeMovie",
          "PageIndex": 1,
          "DisplayPattern": "*suttogva*... milyen vagyok?"
        },
        {
          "DialogueFrom": "MovieReactions/Krobus_*_AfterMovie",
          "DialogueText": "Szóval a fajtád szeret órákon át villogó fényeket bámulni? Nagyon érdekes... {Portrait:Custom:8}",
          "AudioPath": "assets/hu-HU/Krobus/185.ogg",
          "TranslationKey": "Strings/MovieReactions:Krobus_*_AfterMovie",
          "PageIndex": 0,
          "DisplayPattern": "Szóval a fajtád szeret órákon át villogó fényeket bámulni? Nagyon érdekes..."
        }
      ]
    }
  ]
}